[
    {
        "Nome do Produto": "BIOKOSMA - CREME CAPILAR COM EXTRATO DE RAIZ DE BARDANA",
        "Processo": "25351.052724/2006-83",
        "Nome da Empresa - CNPJ": "INDUSTRIA FARMACEUTICA E PERFUMARIA BIOKOSMA LTDA - 64.668.981/0001-22",
        "Número do Registro": "215370111",
        "Situação": "ATIVO",
        "Vencimento": "28/08/2026",
        "link": "https://consultas.anvisa.gov.br/#/cosmeticos/registrados/25351052724200683/?dataInicial=2026-08-28&dataFinal=2026-08-28",
        "Nome da Empresa": "INDÚSTRIA FARMACÊUTICA E PERFUMARIA BIOKOSMA LTDA.",
        "Número do CNPJ da Empresa": "64.668.981/0001-22",
        "Categoria": "CONDICIONADOR COM AÇÃO ANTIQUEDA, ANTICASPA E/OU OUTROS BENEFÍCIOS ESPECÍFICOS QUE JUSTIFIQUEM COMPROVAÇÃO PRÉVIA",
        "Publicação do Registro": "28/08/2006",
        "Vencimento do Registro": "28/08/2026",
        "Situação do Produto": "ATIVO"
    },
    {
        "Nome do Produto": "BIOKOSMA - LOÇÃO CAPILAR COM EXTRATO DE RAIZ DE BARDANA",
        "Processo": "25351.052739/2006-41",
        "Nome da Empresa - CNPJ": "INDUSTRIA FARMACEUTICA E PERFUMARIA BIOKOSMA LTDA - 64.668.981/0001-22",
        "Número do Registro": "215370110",
        "Situação": "ATIVO",
        "Vencimento": "28/08/2026",
        "link": "https://consultas.anvisa.gov.br/#/cosmeticos/registrados/25351052739200641/?dataInicial=2026-08-28&dataFinal=2026-08-28",
        "Nome da Empresa": "INDÚSTRIA FARMACÊUTICA E PERFUMARIA BIOKOSMA LTDA.",
        "Número do CNPJ da Empresa": "64.668.981/0001-22",
        "Categoria": "TÔNICO CAPILAR (ALCOÓLICO OU NÃO)",
        "Publicação do Registro": "28/08/2006",
        "Vencimento do Registro": "28/08/2026",
        "Situação do Produto": "ATIVO"
    },
    {
        "Nome do Produto": "DAVENE CREME PREVENTIVO DE ASSADURAS BEBÊ VIDA",
        "Processo": "25351.272524/2006-45",
        "Nome da Empresa - CNPJ": "CRIA SIM PRODUTOS DE HIGIENE LTDA - 05.975.111/0001-37",
        "Número do Registro": "242110018",
        "Situação": "ATIVO",
        "Vencimento": "28/08/2026",
        "link": "https://consultas.anvisa.gov.br/#/cosmeticos/registrados/25351272524200645/?dataInicial=2026-08-28&dataFinal=2026-08-28",
        "Nome da Empresa": "CRIA SIM PRODUTOS DE HIGIENE LTDA",
        "Número do CNPJ da Empresa": "05.975.111/0001-37",
        "Categoria": "PRODUTO PARA PREVENIR ASSADURAS INFANTIL - GRAU 2",
        "Publicação do Registro": "28/08/2006",
        "Vencimento do Registro": "28/08/2026",
        "Situação do Produto": "ATIVO"
    },
    {
        "Nome do Produto": "DAVENE SABONETE LÍQUIDO SUAVE BEBÊ VIDA",
        "Processo": "25351.273071/2006-74",
        "Nome da Empresa - CNPJ": "CRIA SIM PRODUTOS DE HIGIENE LTDA - 05.975.111/0001-37",
        "Número do Registro": "242110019",
        "Situação": "ATIVO",
        "Vencimento": "28/08/2026",
        "link": "https://consultas.anvisa.gov.br/#/cosmeticos/registrados/25351273071200674/?dataInicial=2026-08-28&dataFinal=2026-08-28",
        "Nome da Empresa": "CRIA SIM PRODUTOS DE HIGIENE LTDA",
        "Número do CNPJ da Empresa": "05.975.111/0001-37",
        "Categoria": "SABONETE INFANTIL - GRAU 2",
        "Publicação do Registro": "28/08/2006",
        "Vencimento do Registro": "28/08/2026",
        "Situação do Produto": "ATIVO"
    },
    {
        "Nome do Produto": "EMODERM CREME",
        "Processo": "25351.267438/2006-11",
        "Nome da Empresa - CNPJ": "THERASKIN FARMACEUTICA LTDA. - 61.517.397/0001-88",
        "Número do Registro": "237080007",
        "Situação": "ATIVO",
        "Vencimento": "28/08/2026",
        "link": "https://consultas.anvisa.gov.br/#/cosmeticos/registrados/25351267438200611/?dataInicial=2026-08-28&dataFinal=2026-08-28",
        "Nome da Empresa": "THERASKIN FARMACEUTICA LTDA.",
        "Número do CNPJ da Empresa": "61.517.397/0001-88",
        "Categoria": "CREME PARA O CORPO COM FINALIDADE EXCLUSIVA DE HIDRATAÇÃO E/OU REFRESCÂNCIA (PERFUMADOS OU NÃO, INCLUINDO OS GÉIS)",
        "Publicação do Registro": "28/08/2006",
        "Vencimento do Registro": "28/08/2026",
        "Situação do Produto": "ATIVO"
    },
    {
        "Nome do Produto": "FANTASY COLOR BOTÂNICA EMULSÃO ATIVADORA 4%",
        "Processo": "25351.282069/2006-96",
        "Nome da Empresa - CNPJ": "IBC INDÚSTRIA BRASILEIRA DE COSMÉTICOS LTDA - EPP - 05.155.875/0001-86",
        "Número do Registro": "238890005",
        "Situação": "ATIVO",
        "Vencimento": "28/08/2026",
        "link": "https://consultas.anvisa.gov.br/#/cosmeticos/registrados/25351282069200696/?dataInicial=2026-08-28&dataFinal=2026-08-28",
        "Nome da Empresa": "IBC INDÚSTRIA BRASILEIRA DE COSMÉTICOS LTDA - EPP",
        "Número do CNPJ da Empresa": "05.155.875/0001-86",
        "Categoria": "OUTROS PRODUTOS NÃO PREVISTOS - GRAU II",
        "Publicação do Registro": "28/08/2006",
        "Vencimento do Registro": "28/08/2026",
        "Situação do Produto": "ATIVO"
    },
    {
        "Nome do Produto": "FANTASY COLOR BOTÂNICA PÓ DESCOLORANTE EXTRA FORTE",
        "Processo": "25351.281751/2006-61",
        "Nome da Empresa - CNPJ": "IBC INDÚSTRIA BRASILEIRA DE COSMÉTICOS LTDA - EPP - 05.155.875/0001-86",
        "Número do Registro": "238890003",
        "Situação": "ATIVO",
        "Vencimento": "28/08/2026",
        "link": "https://consultas.anvisa.gov.br/#/cosmeticos/registrados/25351281751200661/?dataInicial=2026-08-28&dataFinal=2026-08-28",
        "Nome da Empresa": "IBC INDÚSTRIA BRASILEIRA DE COSMÉTICOS LTDA - EPP",
        "Número do CNPJ da Empresa": "05.155.875/0001-86",
        "Categoria": "DESCOLORANTE PARA CABELOS (LÍQUIDO, GEL, CREME OU SÓLIDO)",
        "Publicação do Registro": "28/08/2006",
        "Vencimento do Registro": "28/08/2026",
        "Situação do Produto": "ATIVO"
    },
    {
        "Nome do Produto": "FANTASY COLOR BOTÂNICA PÓ DESCOLORANTE EXTRA SUAVE",
        "Processo": "25351.281817/2006-13",
        "Nome da Empresa - CNPJ": "IBC INDÚSTRIA BRASILEIRA DE COSMÉTICOS LTDA - EPP - 05.155.875/0001-86",
        "Número do Registro": "238890004",
        "Situação": "ATIVO",
        "Vencimento": "28/08/2026",
        "link": "https://consultas.anvisa.gov.br/#/cosmeticos/registrados/25351281817200613/?dataInicial=2026-08-28&dataFinal=2026-08-28",
        "Nome da Empresa": "IBC INDÚSTRIA BRASILEIRA DE COSMÉTICOS LTDA - EPP",
        "Número do CNPJ da Empresa": "05.155.875/0001-86",
        "Categoria": "DESCOLORANTE PARA CABELOS (LÍQUIDO, GEL, CREME OU SÓLIDO)",
        "Publicação do Registro": "28/08/2006",
        "Vencimento do Registro": "28/08/2026",
        "Situação do Produto": "ATIVO"
    },
    {
        "Nome do Produto": "FANTASY COLOR BOTÂNICA ÁGUA OXIGENADA 20 VOL",
        "Processo": "25351.282095/2006-14",
        "Nome da Empresa - CNPJ": "IBC INDÚSTRIA BRASILEIRA DE COSMÉTICOS LTDA - EPP - 05.155.875/0001-86",
        "Número do Registro": "238890006",
        "Situação": "ATIVO",
        "Vencimento": "28/08/2026",
        "link": "https://consultas.anvisa.gov.br/#/cosmeticos/registrados/25351282095200614/?dataInicial=2026-08-28&dataFinal=2026-08-28",
        "Nome da Empresa": "IBC INDÚSTRIA BRASILEIRA DE COSMÉTICOS LTDA - EPP",
        "Número do CNPJ da Empresa": "05.155.875/0001-86",
        "Categoria": "ÁGUA OXIGENADA (10 A 40 VOLUMES) (INCLUÍDAS AS CREMOSAS, EXCETO OS PRODUTOS DE USO MEDICINAL)",
        "Publicação do Registro": "28/08/2006",
        "Vencimento do Registro": "28/08/2026",
        "Situação do Produto": "ATIVO"
    },
    {
        "Nome do Produto": "GEL COM EXTRATO DE ARNICA COM CASTANHA DA ÍNDIA E CÂNFORA DUOTRATO",
        "Processo": "25351.143002/2006-37",
        "Nome da Empresa - CNPJ": "DUOTRATO INDÚSTRIA E COMÉRCIO DE COSMÉTICOS LTDA - ME - 03.223.878/0001-84",
        "Número do Registro": "230200010",
        "Situação": "ATIVO",
        "Vencimento": "28/08/2026",
        "link": "https://consultas.anvisa.gov.br/#/cosmeticos/registrados/25351143002200637/?dataInicial=2026-08-28&dataFinal=2026-08-28",
        "Nome da Empresa": "DUOTRATO INDÚSTRIA E COMÉRCIO DE COSMÉTICOS LTDA - ME",
        "Número do CNPJ da Empresa": "03.223.878/0001-84",
        "Categoria": "CREME PARA O CORPO COM FINALIDADE EXCLUSIVA DE HIDRATAÇÃO E/OU REFRESCÂNCIA (PERFUMADOS OU NÃO, INCLUINDO OS GÉIS)",
        "Publicação do Registro": "28/08/2006",
        "Vencimento do Registro": "28/08/2026",
        "Situação do Produto": "ATIVO"
    },
    {
        "Nome do Produto": "BIOKOSMA - CREME CAPILAR COM EXTRATO DE RAIZ DE BARDANA",
        "Processo": "25351.052724/2006-83",
        "Nome da Empresa - CNPJ": "INDUSTRIA FARMACEUTICA E PERFUMARIA BIOKOSMA LTDA - 64.668.981/0001-22",
        "Número do Registro": "215370111",
        "Situação": "ATIVO",
        "Vencimento": "28/08/2026",
        "link": "https://consultas.anvisa.gov.br/#/cosmeticos/registrados/25351052724200683/?dataInicial=2026-08-28&dataFinal=2026-08-28",
        "Nome da Empresa": "INDÚSTRIA FARMACÊUTICA E PERFUMARIA BIOKOSMA LTDA.",
        "Número do CNPJ da Empresa": "64.668.981/0001-22",
        "Categoria": "CONDICIONADOR COM AÇÃO ANTIQUEDA, ANTICASPA E/OU OUTROS BENEFÍCIOS ESPECÍFICOS QUE JUSTIFIQUEM COMPROVAÇÃO PRÉVIA",
        "Publicação do Registro": "28/08/2006",
        "Vencimento do Registro": "28/08/2026",
        "Situação do Produto": "ATIVO"
    },
    {
        "Nome do Produto": "BIOKOSMA - LOÇÃO CAPILAR COM EXTRATO DE RAIZ DE BARDANA",
        "Processo": "25351.052739/2006-41",
        "Nome da Empresa - CNPJ": "INDUSTRIA FARMACEUTICA E PERFUMARIA BIOKOSMA LTDA - 64.668.981/0001-22",
        "Número do Registro": "215370110",
        "Situação": "ATIVO",
        "Vencimento": "28/08/2026",
        "link": "https://consultas.anvisa.gov.br/#/cosmeticos/registrados/25351052739200641/?dataInicial=2026-08-28&dataFinal=2026-08-28",
        "Nome da Empresa": "INDÚSTRIA FARMACÊUTICA E PERFUMARIA BIOKOSMA LTDA.",
        "Número do CNPJ da Empresa": "64.668.981/0001-22",
        "Categoria": "TÔNICO CAPILAR (ALCOÓLICO OU NÃO)",
        "Publicação do Registro": "28/08/2006",
        "Vencimento do Registro": "28/08/2026",
        "Situação do Produto": "ATIVO"
    },
    {
        "Nome do Produto": "DAVENE CREME PREVENTIVO DE ASSADURAS BEBÊ VIDA",
        "Processo": "25351.272524/2006-45",
        "Nome da Empresa - CNPJ": "CRIA SIM PRODUTOS DE HIGIENE LTDA - 05.975.111/0001-37",
        "Número do Registro": "242110018",
        "Situação": "ATIVO",
        "Vencimento": "28/08/2026",
        "link": "https://consultas.anvisa.gov.br/#/cosmeticos/registrados/25351272524200645/?dataInicial=2026-08-28&dataFinal=2026-08-28",
        "Nome da Empresa": "CRIA SIM PRODUTOS DE HIGIENE LTDA",
        "Número do CNPJ da Empresa": "05.975.111/0001-37",
        "Categoria": "PRODUTO PARA PREVENIR ASSADURAS INFANTIL - GRAU 2",
        "Publicação do Registro": "28/08/2006",
        "Vencimento do Registro": "28/08/2026",
        "Situação do Produto": "ATIVO"
    },
    {
        "Nome do Produto": "DAVENE SABONETE LÍQUIDO SUAVE BEBÊ VIDA",
        "Processo": "25351.273071/2006-74",
        "Nome da Empresa - CNPJ": "CRIA SIM PRODUTOS DE HIGIENE LTDA - 05.975.111/0001-37",
        "Número do Registro": "242110019",
        "Situação": "ATIVO",
        "Vencimento": "28/08/2026",
        "link": "https://consultas.anvisa.gov.br/#/cosmeticos/registrados/25351273071200674/?dataInicial=2026-08-28&dataFinal=2026-08-28",
        "Nome da Empresa": "CRIA SIM PRODUTOS DE HIGIENE LTDA",
        "Número do CNPJ da Empresa": "05.975.111/0001-37",
        "Categoria": "SABONETE INFANTIL - GRAU 2",
        "Publicação do Registro": "28/08/2006",
        "Vencimento do Registro": "28/08/2026",
        "Situação do Produto": "ATIVO"
    },
    {
        "Nome do Produto": "EMODERM CREME",
        "Processo": "25351.267438/2006-11",
        "Nome da Empresa - CNPJ": "THERASKIN FARMACEUTICA LTDA. - 61.517.397/0001-88",
        "Número do Registro": "237080007",
        "Situação": "ATIVO",
        "Vencimento": "28/08/2026",
        "link": "https://consultas.anvisa.gov.br/#/cosmeticos/registrados/25351267438200611/?dataInicial=2026-08-28&dataFinal=2026-08-28",
        "Nome da Empresa": "THERASKIN FARMACEUTICA LTDA.",
        "Número do CNPJ da Empresa": "61.517.397/0001-88",
        "Categoria": "CREME PARA O CORPO COM FINALIDADE EXCLUSIVA DE HIDRATAÇÃO E/OU REFRESCÂNCIA (PERFUMADOS OU NÃO, INCLUINDO OS GÉIS)",
        "Publicação do Registro": "28/08/2006",
        "Vencimento do Registro": "28/08/2026",
        "Situação do Produto": "ATIVO"
    },
    {
        "Nome do Produto": "FANTASY COLOR BOTÂNICA EMULSÃO ATIVADORA 4%",
        "Processo": "25351.282069/2006-96",
        "Nome da Empresa - CNPJ": "IBC INDÚSTRIA BRASILEIRA DE COSMÉTICOS LTDA - EPP - 05.155.875/0001-86",
        "Número do Registro": "238890005",
        "Situação": "ATIVO",
        "Vencimento": "28/08/2026",
        "link": "https://consultas.anvisa.gov.br/#/cosmeticos/registrados/25351282069200696/?dataInicial=2026-08-28&dataFinal=2026-08-28",
        "Nome da Empresa": "IBC INDÚSTRIA BRASILEIRA DE COSMÉTICOS LTDA - EPP",
        "Número do CNPJ da Empresa": "05.155.875/0001-86",
        "Categoria": "OUTROS PRODUTOS NÃO PREVISTOS - GRAU II",
        "Publicação do Registro": "28/08/2006",
        "Vencimento do Registro": "28/08/2026",
        "Situação do Produto": "ATIVO"
    },
    {
        "Nome do Produto": "FANTASY COLOR BOTÂNICA PÓ DESCOLORANTE EXTRA FORTE",
        "Processo": "25351.281751/2006-61",
        "Nome da Empresa - CNPJ": "IBC INDÚSTRIA BRASILEIRA DE COSMÉTICOS LTDA - EPP - 05.155.875/0001-86",
        "Número do Registro": "238890003",
        "Situação": "ATIVO",
        "Vencimento": "28/08/2026",
        "link": "https://consultas.anvisa.gov.br/#/cosmeticos/registrados/25351281751200661/?dataInicial=2026-08-28&dataFinal=2026-08-28",
        "Nome da Empresa": "IBC INDÚSTRIA BRASILEIRA DE COSMÉTICOS LTDA - EPP",
        "Número do CNPJ da Empresa": "05.155.875/0001-86",
        "Categoria": "DESCOLORANTE PARA CABELOS (LÍQUIDO, GEL, CREME OU SÓLIDO)",
        "Publicação do Registro": "28/08/2006",
        "Vencimento do Registro": "28/08/2026",
        "Situação do Produto": "ATIVO"
    },
    {
        "Nome do Produto": "FANTASY COLOR BOTÂNICA PÓ DESCOLORANTE EXTRA SUAVE",
        "Processo": "25351.281817/2006-13",
        "Nome da Empresa - CNPJ": "IBC INDÚSTRIA BRASILEIRA DE COSMÉTICOS LTDA - EPP - 05.155.875/0001-86",
        "Número do Registro": "238890004",
        "Situação": "ATIVO",
        "Vencimento": "28/08/2026",
        "link": "https://consultas.anvisa.gov.br/#/cosmeticos/registrados/25351281817200613/?dataInicial=2026-08-28&dataFinal=2026-08-28",
        "Nome da Empresa": "IBC INDÚSTRIA BRASILEIRA DE COSMÉTICOS LTDA - EPP",
        "Número do CNPJ da Empresa": "05.155.875/0001-86",
        "Categoria": "DESCOLORANTE PARA CABELOS (LÍQUIDO, GEL, CREME OU SÓLIDO)",
        "Publicação do Registro": "28/08/2006",
        "Vencimento do Registro": "28/08/2026",
        "Situação do Produto": "ATIVO"
    },
    {
        "Nome do Produto": "FANTASY COLOR BOTÂNICA ÁGUA OXIGENADA 20 VOL",
        "Processo": "25351.282095/2006-14",
        "Nome da Empresa - CNPJ": "IBC INDÚSTRIA BRASILEIRA DE COSMÉTICOS LTDA - EPP - 05.155.875/0001-86",
        "Número do Registro": "238890006",
        "Situação": "ATIVO",
        "Vencimento": "28/08/2026",
        "link": "https://consultas.anvisa.gov.br/#/cosmeticos/registrados/25351282095200614/?dataInicial=2026-08-28&dataFinal=2026-08-28",
        "Nome da Empresa": "IBC INDÚSTRIA BRASILEIRA DE COSMÉTICOS LTDA - EPP",
        "Número do CNPJ da Empresa": "05.155.875/0001-86",
        "Categoria": "ÁGUA OXIGENADA (10 A 40 VOLUMES) (INCLUÍDAS AS CREMOSAS, EXCETO OS PRODUTOS DE USO MEDICINAL)",
        "Publicação do Registro": "28/08/2006",
        "Vencimento do Registro": "28/08/2026",
        "Situação do Produto": "ATIVO"
    },
    {
        "Nome do Produto": "GEL COM EXTRATO DE ARNICA COM CASTANHA DA ÍNDIA E CÂNFORA DUOTRATO",
        "Processo": "25351.143002/2006-37",
        "Nome da Empresa - CNPJ": "DUOTRATO INDÚSTRIA E COMÉRCIO DE COSMÉTICOS LTDA - ME - 03.223.878/0001-84",
        "Número do Registro": "230200010",
        "Situação": "ATIVO",
        "Vencimento": "28/08/2026",
        "link": "https://consultas.anvisa.gov.br/#/cosmeticos/registrados/25351143002200637/?dataInicial=2026-08-28&dataFinal=2026-08-28",
        "Nome da Empresa": "DUOTRATO INDÚSTRIA E COMÉRCIO DE COSMÉTICOS LTDA - ME",
        "Número do CNPJ da Empresa": "03.223.878/0001-84",
        "Categoria": "CREME PARA O CORPO COM FINALIDADE EXCLUSIVA DE HIDRATAÇÃO E/OU REFRESCÂNCIA (PERFUMADOS OU NÃO, INCLUINDO OS GÉIS)",
        "Publicação do Registro": "28/08/2006",
        "Vencimento do Registro": "28/08/2026",
        "Situação do Produto": "ATIVO"
    },
    {
        "Nome do Produto": "GEL REDUTOR PARA O CORPO D´AGUA NATURAL",
        "Processo": "25351.305432/2006-59",
        "Nome da Empresa - CNPJ": "ROCHADEL COMERCIO E INDUSTRIA DE COSMETICOS LTDA. - 90.278.284/0001-75",
        "Número do Registro": "213800040",
        "Situação": "ATIVO",
        "Vencimento": "28/08/2026",
        "link": "https://consultas.anvisa.gov.br/#/cosmeticos/registrados/25351305432200659/?dataInicial=2026-08-28&dataFinal=2026-08-28",
        "Nome da Empresa": "ROCHADEL COMERCIO E INDUSTRIA DE COSMETICOS LTDA.",
        "Número do CNPJ da Empresa": "90.278.284/0001-75",
        "Categoria": "CREME PARA CELULITE / ESTRIAS (PERFUMADOS OU NÃO, INCLUINDO OS GÉIS)",
        "Publicação do Registro": "28/08/2006",
        "Vencimento do Registro": "28/08/2026",
        "Situação do Produto": "ATIVO"
    },
    {
        "Nome do Produto": "SABONETE LÍQUIDO PARA ANTI SEPSIA PEROL PLEASANT",
        "Processo": "25351.144591/2006-71",
        "Nome da Empresa - CNPJ": "PEROL COMERCIAL E INDUSTRIAL LTDA - ME - 01.320.978/0001-01",
        "Número do Registro": "241260001",
        "Situação": "ATIVO",
        "Vencimento": "28/08/2026",
        "link": "https://consultas.anvisa.gov.br/#/cosmeticos/registrados/25351144591200671/?dataInicial=2026-08-28&dataFinal=2026-08-28",
        "Nome da Empresa": "PEROL COMERCIAL E INDUSTRIAL LTDA - ME",
        "Número do CNPJ da Empresa": "01.320.978/0001-01",
        "Categoria": "SABONETE FACIAL E/OU CORPORAL ANTI-SÉPTICO (LÍQUIDO,GEL, CREME OU SÓLIDO)",
        "Publicação do Registro": "28/08/2006",
        "Vencimento do Registro": "28/08/2026",
        "Situação do Produto": "ATIVO"
    }
]