[
    {
        "Nome do Produto": "BROMELIN PRÓPOLIS SPRAY AROMATIZANTE BUCAL",
        "Processo": "25351.064766/2006-67",
        "Nome da Empresa - CNPJ": "INFAN INDUSTRIA QUIMICA FARMACEUTICA NACIONAL S/A - 08.939.548/0001-03",
        "Número do Registro": "236310006",
        "Situação": "ATIVO",
        "Vencimento": "13/11/2026",
        "link": "https://consultas.anvisa.gov.br/#/cosmeticos/registrados/25351064766200667/?dataInicial=2026-11-13&dataFinal=2026-11-13",
        "Nome da Empresa": "INFAN INDUSTRIA QUIMICA FARMACEUTICA NACIONAL S/A",
        "Número do CNPJ da Empresa": "08.939.548/0001-03",
        "Categoria": "AROMATIZANTE BUCAL SEM AÇÃO ANTI-SÉPTICA (LÍQUIDO, GEL, CREME, SÓLIDO OU AEROSSOL)",
        "Publicação do Registro": "13/11/2006",
        "Vencimento do Registro": "13/11/2026",
        "Situação do Produto": "ATIVO"
    },
    {
        "Nome do Produto": "LA PRAIRIE EXTRAIT OF SKIN CAVIAR FIRMING COMPLEX",
        "Processo": "25351.412614/2006-85",
        "Nome da Empresa - CNPJ": "BRIGHT STAR BUSINESS CORP. DO BRASIL PERFUMARIA E ALIMENTOS LTDA - 04.292.882/0001-67",
        "Número do Registro": "239400059",
        "Situação": "ATIVO",
        "Vencimento": "13/11/2026",
        "link": "https://consultas.anvisa.gov.br/#/cosmeticos/registrados/25351412614200685/?dataInicial=2026-11-13&dataFinal=2026-11-13",
        "Nome da Empresa": "BRIGHT STAR BUSINESS CORP. DO BRASIL PERFUMARIA E ALIMENTOS LTDA",
        "Número do CNPJ da Empresa": "04.292.882/0001-67",
        "Categoria": "LOÇÃO PARA O ROSTO SEM AÇÃO FOTOPROTETORA DA PELE E COM FINALIDADE EXCLUSIVA DE HIDRATAÇÃO E/OU REFRESCÂNCIA (ALCOÓLICAS OU NÃO, EMULSIONADAS OU NÃO, INCLUINDO OS \"LEITES\")",
        "Publicação do Registro": "13/11/2006",
        "Vencimento do Registro": "13/11/2026",
        "Situação do Produto": "ATIVO"
    },
    {
        "Nome do Produto": "LABY PROTETOR SOLAR LABIAL FPS 30 MORANGO",
        "Processo": "25351.343055/2006-56",
        "Nome da Empresa - CNPJ": "BRAVIR INDUSTRIAL LTDA - 18.688.481/0001-35",
        "Número do Registro": "206420019",
        "Situação": "INATIVO",
        "Vencimento": "13/11/2026",
        "link": "https://consultas.anvisa.gov.br/#/cosmeticos/registrados/25351343055200656/?dataInicial=2026-11-13&dataFinal=2026-11-13",
        "Nome da Empresa": "BRAVIR INDUSTRIAL LTDA",
        "Número do CNPJ da Empresa": "18.688.481/0001-35",
        "Categoria": "PROTETOR LABIAL COM AÇÃO FOTOPROTETORA (LÍQUIDO, GEL, CREME OU SÓLIDO)",
        "Publicação do Registro": "13/11/2006",
        "Vencimento do Registro": "13/11/2026",
        "Situação do Produto": "INATIVO"
    }
]