[
    {
        "Nome do Produto": "CREME PROTETOR DERMAMON FREE",
        "Processo": "25351.264515/2004-19",
        "Nome da Empresa - CNPJ": "DBS INDÚSTRIA E COMÉRCIO LTDA - 05.210.556/0001-26",
        "Número do Registro": "236160004",
        "Situação": "ATIVO",
        "Vencimento": "19/01/2030",
        "link": "https://consultas.anvisa.gov.br/#/cosmeticos/registrados/25351264515200419/?dataInicial=2030-01-19&dataFinal=2030-01-19",
        "Nome da Empresa": "DBS INDÚSTRIA E COMÉRCIO LTDA",
        "Número do CNPJ da Empresa": "05.210.556/0001-26",
        "Categoria": "OUTROS PRODUTOS NÃO PREVISTOS - GRAU II",
        "Publicação do Registro": "19/01/2005",
        "Vencimento do Registro": "19/01/2030",
        "Situação do Produto": "ATIVO"
    }
]