[
    {
        "Nome do Produto": "CLINERIZE CUIDADO TOTAL 6 EM 1",
        "Processo": "25351.278193/2009-86",
        "Nome da Empresa - CNPJ": "CIFARMA CIENTÍFICA FARMACÊUTICA LTDA - 17.562.075/0001-69",
        "Número do Registro": "241300008",
        "Situação": "ATIVO",
        "Vencimento": "13/10/2029",
        "link": "https://consultas.anvisa.gov.br/#/cosmeticos/registrados/25351278193200986/?dataInicial=2029-10-13&dataFinal=2029-10-13",
        "Nome da Empresa": "CIFARMA CIENTÍFICA FARMACÊUTICA LTDA",
        "Número do CNPJ da Empresa": "17.562.075/0001-69",
        "Categoria": "ENXAGUATÓRIO BUCAL COM FLÚOR, ANTIPLACA E ANTI-SÉPTICO",
        "Publicação do Registro": "13/10/2009",
        "Vencimento do Registro": "13/10/2029",
        "Situação do Produto": "ATIVO"
    },
    {
        "Nome do Produto": "CLINERIZE HORTELÃ COM FLÚOR",
        "Processo": "25351.166214/2009-04",
        "Nome da Empresa - CNPJ": "CIFARMA CIENTÍFICA FARMACÊUTICA LTDA - 17.562.075/0001-69",
        "Número do Registro": "241300006",
        "Situação": "ATIVO",
        "Vencimento": "13/10/2029",
        "link": "https://consultas.anvisa.gov.br/#/cosmeticos/registrados/25351166214200904/?dataInicial=2029-10-13&dataFinal=2029-10-13",
        "Nome da Empresa": "CIFARMA CIENTÍFICA FARMACÊUTICA LTDA",
        "Número do CNPJ da Empresa": "17.562.075/0001-69",
        "Categoria": "ENXAGUATÓRIO BUCAL COM FLÚOR, ANTIPLACA E ANTI-SÉPTICO",
        "Publicação do Registro": "13/10/2009",
        "Vencimento do Registro": "13/10/2029",
        "Situação do Produto": "ATIVO"
    },
    {
        "Nome do Produto": "CLINERIZE MENTA",
        "Processo": "25351.166193/2009-15",
        "Nome da Empresa - CNPJ": "CIFARMA CIENTÍFICA FARMACÊUTICA LTDA - 17.562.075/0001-69",
        "Número do Registro": "241300004",
        "Situação": "ATIVO",
        "Vencimento": "13/10/2029",
        "link": "https://consultas.anvisa.gov.br/#/cosmeticos/registrados/25351166193200915/?dataInicial=2029-10-13&dataFinal=2029-10-13",
        "Nome da Empresa": "CIFARMA CIENTÍFICA FARMACÊUTICA LTDA",
        "Número do CNPJ da Empresa": "17.562.075/0001-69",
        "Categoria": "ENXAGUATÓRIO BUCAL COM FLÚOR, ANTIPLACA E ANTI-SÉPTICO",
        "Publicação do Registro": "13/10/2009",
        "Vencimento do Registro": "13/10/2029",
        "Situação do Produto": "ATIVO"
    },
    {
        "Nome do Produto": "CLINERIZE MENTA E HORTELÃ",
        "Processo": "25351.166197/2009-15",
        "Nome da Empresa - CNPJ": "CIFARMA CIENTÍFICA FARMACÊUTICA LTDA - 17.562.075/0001-69",
        "Número do Registro": "241300005",
        "Situação": "ATIVO",
        "Vencimento": "13/10/2029",
        "link": "https://consultas.anvisa.gov.br/#/cosmeticos/registrados/25351166197200915/?dataInicial=2029-10-13&dataFinal=2029-10-13",
        "Nome da Empresa": "CIFARMA CIENTÍFICA FARMACÊUTICA LTDA",
        "Número do CNPJ da Empresa": "17.562.075/0001-69",
        "Categoria": "ENXAGUATÓRIO BUCAL COM FLÚOR, ANTIPLACA E ANTI-SÉPTICO",
        "Publicação do Registro": "13/10/2009",
        "Vencimento do Registro": "13/10/2029",
        "Situação do Produto": "ATIVO"
    },
    {
        "Nome do Produto": "CLINERIZE MENTA SUAVE",
        "Processo": "25351.166222/2009-61",
        "Nome da Empresa - CNPJ": "CIFARMA CIENTÍFICA FARMACÊUTICA LTDA - 17.562.075/0001-69",
        "Número do Registro": "241300007",
        "Situação": "ATIVO",
        "Vencimento": "13/10/2029",
        "link": "https://consultas.anvisa.gov.br/#/cosmeticos/registrados/25351166222200961/?dataInicial=2029-10-13&dataFinal=2029-10-13",
        "Nome da Empresa": "CIFARMA CIENTÍFICA FARMACÊUTICA LTDA",
        "Número do CNPJ da Empresa": "17.562.075/0001-69",
        "Categoria": "ENXAGUATÓRIO BUCAL COM FLÚOR, ANTIPLACA E ANTI-SÉPTICO",
        "Publicação do Registro": "13/10/2009",
        "Vencimento do Registro": "13/10/2029",
        "Situação do Produto": "ATIVO"
    },
    {
        "Nome do Produto": "CLINERIZE TRADICIONAL",
        "Processo": "25351.166185/2009-45",
        "Nome da Empresa - CNPJ": "CIFARMA CIENTÍFICA FARMACÊUTICA LTDA - 17.562.075/0001-69",
        "Número do Registro": "241300003",
        "Situação": "ATIVO",
        "Vencimento": "13/10/2029",
        "link": "https://consultas.anvisa.gov.br/#/cosmeticos/registrados/25351166185200945/?dataInicial=2029-10-13&dataFinal=2029-10-13",
        "Nome da Empresa": "CIFARMA CIENTÍFICA FARMACÊUTICA LTDA",
        "Número do CNPJ da Empresa": "17.562.075/0001-69",
        "Categoria": "ENXAGUATÓRIO BUCAL COM FLÚOR, ANTIPLACA E ANTI-SÉPTICO",
        "Publicação do Registro": "13/10/2009",
        "Vencimento do Registro": "13/10/2029",
        "Situação do Produto": "ATIVO"
    },
    {
        "Nome do Produto": "LUMIFACE LOÇÃO CREMOSA NUTRITIVA E HIDRATANTE KOSMENTAL AEROSSOL",
        "Processo": "25351.363321/2009-17",
        "Nome da Empresa - CNPJ": "KOOSMETICS INDÚSTRIA E COMÉRCIO DE COSMÉTICOS IMPORTAÇÃO E EXPORTAÇÃO LTDA - 05.297.188/0001-03",
        "Número do Registro": "235140005",
        "Situação": "ATIVO",
        "Vencimento": "13/10/2029",
        "link": "https://consultas.anvisa.gov.br/#/cosmeticos/registrados/25351363321200917/?dataInicial=2029-10-13&dataFinal=2029-10-13",
        "Nome da Empresa": "KOOSMETICS INDÚSTRIA E COMÉRCIO DE COSMÉTICOS IMPORTAÇÃO E EXPORTAÇÃO LTDA",
        "Número do CNPJ da Empresa": "05.297.188/0001-03",
        "Categoria": "CREME OU LOÇÃO PARA O ROSTO COM FOTOPROTETOR DA PELE E/ou COM OUTRAS FINALIDADES ALÉM DA HIDRATAÇÃO (PERFUMADOS OU NÃO, INCLUINDO OS GÉIS)",
        "Publicação do Registro": "13/10/2009",
        "Vencimento do Registro": "13/10/2029",
        "Situação do Produto": "ATIVO"
    },
    {
        "Nome do Produto": "PROTETOR SOLAR FPS 60 RED APPLE",
        "Processo": "25351.391005/2009-25",
        "Nome da Empresa - CNPJ": "COSINTER INTERNACIONAL IND E COM COSMETICOS LTDA - 85.080.836/0001-04",
        "Número do Registro": "216760159",
        "Situação": "ATIVO",
        "Vencimento": "13/10/2029",
        "link": "https://consultas.anvisa.gov.br/#/cosmeticos/registrados/25351391005200925/?dataInicial=2029-10-13&dataFinal=2029-10-13",
        "Nome da Empresa": "COSINTER INTERNACIONAL INDÚSTRIA E COMÉRCIO DE COSMÉTICOS LTDA",
        "Número do CNPJ da Empresa": "85.080.836/0001-04",
        "Categoria": "PROTETOR SOLAR",
        "Publicação do Registro": "13/10/2009",
        "Vencimento do Registro": "13/10/2029",
        "Situação do Produto": "ATIVO"
    },
    {
        "Nome do Produto": "PÓ DESCOLORANTE FAST BLOND CONCEPT PROFISSIONAL",
        "Processo": "25351.273825/2009-77",
        "Nome da Empresa - CNPJ": "ESSENCIALLE INDUSTRIA E COMERCIO DE COSMETICOS LTDA - 07.604.482/0001-38",
        "Número do Registro": "248940001",
        "Situação": "ATIVO",
        "Vencimento": "13/10/2029",
        "link": "https://consultas.anvisa.gov.br/#/cosmeticos/registrados/25351273825200977/?dataInicial=2029-10-13&dataFinal=2029-10-13",
        "Nome da Empresa": "ESSENCIALLE INDUSTRIA E COMERCIO DE COSMETICOS LTDA",
        "Número do CNPJ da Empresa": "07.604.482/0001-38",
        "Categoria": "CLAREADOR PARA CABELOS (LÍQUIDO, GEL, CREME OU SÓLIDO)",
        "Publicação do Registro": "13/10/2009",
        "Vencimento do Registro": "13/10/2029",
        "Situação do Produto": "ATIVO"
    },
    {
        "Nome do Produto": "RELAXER PREMIUM CALCIUM TREATMENT SYSTEM - CREME DE RELAXAMENTO CAPILAR NUTRAT",
        "Processo": "25351.421977/2009-30",
        "Nome da Empresa - CNPJ": "PROLAB INDÚSTRIA E COMÉRCIO DE COSMÉTICOS LTDA - 64.988.678/0001-07",
        "Número do Registro": "232410023",
        "Situação": "ATIVO",
        "Vencimento": "13/10/2029",
        "link": "https://consultas.anvisa.gov.br/#/cosmeticos/registrados/25351421977200930/?dataInicial=2029-10-13&dataFinal=2029-10-13",
        "Nome da Empresa": "PROLAB INDÚSTRIA E COMÉRCIO DE COSMÉTICOS LTDA",
        "Número do CNPJ da Empresa": "64.988.678/0001-07",
        "Categoria": "ALISANTE PARA CABELOS - GRAU 2",
        "Publicação do Registro": "13/10/2009",
        "Vencimento do Registro": "13/10/2029",
        "Situação do Produto": "ATIVO"
    },
    {
        "Nome do Produto": "CLINERIZE CUIDADO TOTAL 6 EM 1",
        "Processo": "25351.278193/2009-86",
        "Nome da Empresa - CNPJ": "CIFARMA CIENTÍFICA FARMACÊUTICA LTDA - 17.562.075/0001-69",
        "Número do Registro": "241300008",
        "Situação": "ATIVO",
        "Vencimento": "13/10/2029",
        "link": "https://consultas.anvisa.gov.br/#/cosmeticos/registrados/25351278193200986/?dataInicial=2029-10-13&dataFinal=2029-10-13",
        "Nome da Empresa": "CIFARMA CIENTÍFICA FARMACÊUTICA LTDA",
        "Número do CNPJ da Empresa": "17.562.075/0001-69",
        "Categoria": "ENXAGUATÓRIO BUCAL COM FLÚOR, ANTIPLACA E ANTI-SÉPTICO",
        "Publicação do Registro": "13/10/2009",
        "Vencimento do Registro": "13/10/2029",
        "Situação do Produto": "ATIVO"
    },
    {
        "Nome do Produto": "CLINERIZE HORTELÃ COM FLÚOR",
        "Processo": "25351.166214/2009-04",
        "Nome da Empresa - CNPJ": "CIFARMA CIENTÍFICA FARMACÊUTICA LTDA - 17.562.075/0001-69",
        "Número do Registro": "241300006",
        "Situação": "ATIVO",
        "Vencimento": "13/10/2029",
        "link": "https://consultas.anvisa.gov.br/#/cosmeticos/registrados/25351166214200904/?dataInicial=2029-10-13&dataFinal=2029-10-13",
        "Nome da Empresa": "CIFARMA CIENTÍFICA FARMACÊUTICA LTDA",
        "Número do CNPJ da Empresa": "17.562.075/0001-69",
        "Categoria": "ENXAGUATÓRIO BUCAL COM FLÚOR, ANTIPLACA E ANTI-SÉPTICO",
        "Publicação do Registro": "13/10/2009",
        "Vencimento do Registro": "13/10/2029",
        "Situação do Produto": "ATIVO"
    },
    {
        "Nome do Produto": "CLINERIZE MENTA",
        "Processo": "25351.166193/2009-15",
        "Nome da Empresa - CNPJ": "CIFARMA CIENTÍFICA FARMACÊUTICA LTDA - 17.562.075/0001-69",
        "Número do Registro": "241300004",
        "Situação": "ATIVO",
        "Vencimento": "13/10/2029",
        "link": "https://consultas.anvisa.gov.br/#/cosmeticos/registrados/25351166193200915/?dataInicial=2029-10-13&dataFinal=2029-10-13",
        "Nome da Empresa": "CIFARMA CIENTÍFICA FARMACÊUTICA LTDA",
        "Número do CNPJ da Empresa": "17.562.075/0001-69",
        "Categoria": "ENXAGUATÓRIO BUCAL COM FLÚOR, ANTIPLACA E ANTI-SÉPTICO",
        "Publicação do Registro": "13/10/2009",
        "Vencimento do Registro": "13/10/2029",
        "Situação do Produto": "ATIVO"
    },
    {
        "Nome do Produto": "CLINERIZE MENTA E HORTELÃ",
        "Processo": "25351.166197/2009-15",
        "Nome da Empresa - CNPJ": "CIFARMA CIENTÍFICA FARMACÊUTICA LTDA - 17.562.075/0001-69",
        "Número do Registro": "241300005",
        "Situação": "ATIVO",
        "Vencimento": "13/10/2029",
        "link": "https://consultas.anvisa.gov.br/#/cosmeticos/registrados/25351166197200915/?dataInicial=2029-10-13&dataFinal=2029-10-13",
        "Nome da Empresa": "CIFARMA CIENTÍFICA FARMACÊUTICA LTDA",
        "Número do CNPJ da Empresa": "17.562.075/0001-69",
        "Categoria": "ENXAGUATÓRIO BUCAL COM FLÚOR, ANTIPLACA E ANTI-SÉPTICO",
        "Publicação do Registro": "13/10/2009",
        "Vencimento do Registro": "13/10/2029",
        "Situação do Produto": "ATIVO"
    },
    {
        "Nome do Produto": "CLINERIZE MENTA SUAVE",
        "Processo": "25351.166222/2009-61",
        "Nome da Empresa - CNPJ": "CIFARMA CIENTÍFICA FARMACÊUTICA LTDA - 17.562.075/0001-69",
        "Número do Registro": "241300007",
        "Situação": "ATIVO",
        "Vencimento": "13/10/2029",
        "link": "https://consultas.anvisa.gov.br/#/cosmeticos/registrados/25351166222200961/?dataInicial=2029-10-13&dataFinal=2029-10-13",
        "Nome da Empresa": "CIFARMA CIENTÍFICA FARMACÊUTICA LTDA",
        "Número do CNPJ da Empresa": "17.562.075/0001-69",
        "Categoria": "ENXAGUATÓRIO BUCAL COM FLÚOR, ANTIPLACA E ANTI-SÉPTICO",
        "Publicação do Registro": "13/10/2009",
        "Vencimento do Registro": "13/10/2029",
        "Situação do Produto": "ATIVO"
    },
    {
        "Nome do Produto": "CLINERIZE TRADICIONAL",
        "Processo": "25351.166185/2009-45",
        "Nome da Empresa - CNPJ": "CIFARMA CIENTÍFICA FARMACÊUTICA LTDA - 17.562.075/0001-69",
        "Número do Registro": "241300003",
        "Situação": "ATIVO",
        "Vencimento": "13/10/2029",
        "link": "https://consultas.anvisa.gov.br/#/cosmeticos/registrados/25351166185200945/?dataInicial=2029-10-13&dataFinal=2029-10-13",
        "Nome da Empresa": "CIFARMA CIENTÍFICA FARMACÊUTICA LTDA",
        "Número do CNPJ da Empresa": "17.562.075/0001-69",
        "Categoria": "ENXAGUATÓRIO BUCAL COM FLÚOR, ANTIPLACA E ANTI-SÉPTICO",
        "Publicação do Registro": "13/10/2009",
        "Vencimento do Registro": "13/10/2029",
        "Situação do Produto": "ATIVO"
    },
    {
        "Nome do Produto": "LUMIFACE LOÇÃO CREMOSA NUTRITIVA E HIDRATANTE KOSMENTAL AEROSSOL",
        "Processo": "25351.363321/2009-17",
        "Nome da Empresa - CNPJ": "KOOSMETICS INDÚSTRIA E COMÉRCIO DE COSMÉTICOS IMPORTAÇÃO E EXPORTAÇÃO LTDA - 05.297.188/0001-03",
        "Número do Registro": "235140005",
        "Situação": "ATIVO",
        "Vencimento": "13/10/2029",
        "link": "https://consultas.anvisa.gov.br/#/cosmeticos/registrados/25351363321200917/?dataInicial=2029-10-13&dataFinal=2029-10-13",
        "Nome da Empresa": "KOOSMETICS INDÚSTRIA E COMÉRCIO DE COSMÉTICOS IMPORTAÇÃO E EXPORTAÇÃO LTDA",
        "Número do CNPJ da Empresa": "05.297.188/0001-03",
        "Categoria": "CREME OU LOÇÃO PARA O ROSTO COM FOTOPROTETOR DA PELE E/ou COM OUTRAS FINALIDADES ALÉM DA HIDRATAÇÃO (PERFUMADOS OU NÃO, INCLUINDO OS GÉIS)",
        "Publicação do Registro": "13/10/2009",
        "Vencimento do Registro": "13/10/2029",
        "Situação do Produto": "ATIVO"
    },
    {
        "Nome do Produto": "PROTETOR SOLAR FPS 60 RED APPLE",
        "Processo": "25351.391005/2009-25",
        "Nome da Empresa - CNPJ": "COSINTER INTERNACIONAL IND E COM COSMETICOS LTDA - 85.080.836/0001-04",
        "Número do Registro": "216760159",
        "Situação": "ATIVO",
        "Vencimento": "13/10/2029",
        "link": "https://consultas.anvisa.gov.br/#/cosmeticos/registrados/25351391005200925/?dataInicial=2029-10-13&dataFinal=2029-10-13",
        "Nome da Empresa": "COSINTER INTERNACIONAL INDÚSTRIA E COMÉRCIO DE COSMÉTICOS LTDA",
        "Número do CNPJ da Empresa": "85.080.836/0001-04",
        "Categoria": "PROTETOR SOLAR",
        "Publicação do Registro": "13/10/2009",
        "Vencimento do Registro": "13/10/2029",
        "Situação do Produto": "ATIVO"
    },
    {
        "Nome do Produto": "PÓ DESCOLORANTE FAST BLOND CONCEPT PROFISSIONAL",
        "Processo": "25351.273825/2009-77",
        "Nome da Empresa - CNPJ": "ESSENCIALLE INDUSTRIA E COMERCIO DE COSMETICOS LTDA - 07.604.482/0001-38",
        "Número do Registro": "248940001",
        "Situação": "ATIVO",
        "Vencimento": "13/10/2029",
        "link": "https://consultas.anvisa.gov.br/#/cosmeticos/registrados/25351273825200977/?dataInicial=2029-10-13&dataFinal=2029-10-13",
        "Nome da Empresa": "ESSENCIALLE INDUSTRIA E COMERCIO DE COSMETICOS LTDA",
        "Número do CNPJ da Empresa": "07.604.482/0001-38",
        "Categoria": "CLAREADOR PARA CABELOS (LÍQUIDO, GEL, CREME OU SÓLIDO)",
        "Publicação do Registro": "13/10/2009",
        "Vencimento do Registro": "13/10/2029",
        "Situação do Produto": "ATIVO"
    },
    {
        "Nome do Produto": "RELAXER PREMIUM CALCIUM TREATMENT SYSTEM - CREME DE RELAXAMENTO CAPILAR NUTRAT",
        "Processo": "25351.421977/2009-30",
        "Nome da Empresa - CNPJ": "PROLAB INDÚSTRIA E COMÉRCIO DE COSMÉTICOS LTDA - 64.988.678/0001-07",
        "Número do Registro": "232410023",
        "Situação": "ATIVO",
        "Vencimento": "13/10/2029",
        "link": "https://consultas.anvisa.gov.br/#/cosmeticos/registrados/25351421977200930/?dataInicial=2029-10-13&dataFinal=2029-10-13",
        "Nome da Empresa": "PROLAB INDÚSTRIA E COMÉRCIO DE COSMÉTICOS LTDA",
        "Número do CNPJ da Empresa": "64.988.678/0001-07",
        "Categoria": "ALISANTE PARA CABELOS - GRAU 2",
        "Publicação do Registro": "13/10/2009",
        "Vencimento do Registro": "13/10/2029",
        "Situação do Produto": "ATIVO"
    },
    {
        "Nome do Produto": "CLINERIZE CUIDADO TOTAL 6 EM 1",
        "Processo": "25351.278193/2009-86",
        "Nome da Empresa - CNPJ": "CIFARMA CIENTÍFICA FARMACÊUTICA LTDA - 17.562.075/0001-69",
        "Número do Registro": "241300008",
        "Situação": "ATIVO",
        "Vencimento": "13/10/2029",
        "link": "https://consultas.anvisa.gov.br/#/cosmeticos/registrados/25351278193200986/?dataInicial=2029-10-13&dataFinal=2029-10-13",
        "Nome da Empresa": "CIFARMA CIENTÍFICA FARMACÊUTICA LTDA",
        "Número do CNPJ da Empresa": "17.562.075/0001-69",
        "Categoria": "ENXAGUATÓRIO BUCAL COM FLÚOR, ANTIPLACA E ANTI-SÉPTICO",
        "Publicação do Registro": "13/10/2009",
        "Vencimento do Registro": "13/10/2029",
        "Situação do Produto": "ATIVO"
    },
    {
        "Nome do Produto": "CLINERIZE HORTELÃ COM FLÚOR",
        "Processo": "25351.166214/2009-04",
        "Nome da Empresa - CNPJ": "CIFARMA CIENTÍFICA FARMACÊUTICA LTDA - 17.562.075/0001-69",
        "Número do Registro": "241300006",
        "Situação": "ATIVO",
        "Vencimento": "13/10/2029",
        "link": "https://consultas.anvisa.gov.br/#/cosmeticos/registrados/25351166214200904/?dataInicial=2029-10-13&dataFinal=2029-10-13",
        "Nome da Empresa": "CIFARMA CIENTÍFICA FARMACÊUTICA LTDA",
        "Número do CNPJ da Empresa": "17.562.075/0001-69",
        "Categoria": "ENXAGUATÓRIO BUCAL COM FLÚOR, ANTIPLACA E ANTI-SÉPTICO",
        "Publicação do Registro": "13/10/2009",
        "Vencimento do Registro": "13/10/2029",
        "Situação do Produto": "ATIVO"
    },
    {
        "Nome do Produto": "CLINERIZE MENTA",
        "Processo": "25351.166193/2009-15",
        "Nome da Empresa - CNPJ": "CIFARMA CIENTÍFICA FARMACÊUTICA LTDA - 17.562.075/0001-69",
        "Número do Registro": "241300004",
        "Situação": "ATIVO",
        "Vencimento": "13/10/2029",
        "link": "https://consultas.anvisa.gov.br/#/cosmeticos/registrados/25351166193200915/?dataInicial=2029-10-13&dataFinal=2029-10-13",
        "Nome da Empresa": "CIFARMA CIENTÍFICA FARMACÊUTICA LTDA",
        "Número do CNPJ da Empresa": "17.562.075/0001-69",
        "Categoria": "ENXAGUATÓRIO BUCAL COM FLÚOR, ANTIPLACA E ANTI-SÉPTICO",
        "Publicação do Registro": "13/10/2009",
        "Vencimento do Registro": "13/10/2029",
        "Situação do Produto": "ATIVO"
    },
    {
        "Nome do Produto": "CLINERIZE MENTA E HORTELÃ",
        "Processo": "25351.166197/2009-15",
        "Nome da Empresa - CNPJ": "CIFARMA CIENTÍFICA FARMACÊUTICA LTDA - 17.562.075/0001-69",
        "Número do Registro": "241300005",
        "Situação": "ATIVO",
        "Vencimento": "13/10/2029",
        "link": "https://consultas.anvisa.gov.br/#/cosmeticos/registrados/25351166197200915/?dataInicial=2029-10-13&dataFinal=2029-10-13",
        "Nome da Empresa": "CIFARMA CIENTÍFICA FARMACÊUTICA LTDA",
        "Número do CNPJ da Empresa": "17.562.075/0001-69",
        "Categoria": "ENXAGUATÓRIO BUCAL COM FLÚOR, ANTIPLACA E ANTI-SÉPTICO",
        "Publicação do Registro": "13/10/2009",
        "Vencimento do Registro": "13/10/2029",
        "Situação do Produto": "ATIVO"
    },
    {
        "Nome do Produto": "CLINERIZE MENTA SUAVE",
        "Processo": "25351.166222/2009-61",
        "Nome da Empresa - CNPJ": "CIFARMA CIENTÍFICA FARMACÊUTICA LTDA - 17.562.075/0001-69",
        "Número do Registro": "241300007",
        "Situação": "ATIVO",
        "Vencimento": "13/10/2029",
        "link": "https://consultas.anvisa.gov.br/#/cosmeticos/registrados/25351166222200961/?dataInicial=2029-10-13&dataFinal=2029-10-13",
        "Nome da Empresa": "CIFARMA CIENTÍFICA FARMACÊUTICA LTDA",
        "Número do CNPJ da Empresa": "17.562.075/0001-69",
        "Categoria": "ENXAGUATÓRIO BUCAL COM FLÚOR, ANTIPLACA E ANTI-SÉPTICO",
        "Publicação do Registro": "13/10/2009",
        "Vencimento do Registro": "13/10/2029",
        "Situação do Produto": "ATIVO"
    },
    {
        "Nome do Produto": "CLINERIZE TRADICIONAL",
        "Processo": "25351.166185/2009-45",
        "Nome da Empresa - CNPJ": "CIFARMA CIENTÍFICA FARMACÊUTICA LTDA - 17.562.075/0001-69",
        "Número do Registro": "241300003",
        "Situação": "ATIVO",
        "Vencimento": "13/10/2029",
        "link": "https://consultas.anvisa.gov.br/#/cosmeticos/registrados/25351166185200945/?dataInicial=2029-10-13&dataFinal=2029-10-13",
        "Nome da Empresa": "CIFARMA CIENTÍFICA FARMACÊUTICA LTDA",
        "Número do CNPJ da Empresa": "17.562.075/0001-69",
        "Categoria": "ENXAGUATÓRIO BUCAL COM FLÚOR, ANTIPLACA E ANTI-SÉPTICO",
        "Publicação do Registro": "13/10/2009",
        "Vencimento do Registro": "13/10/2029",
        "Situação do Produto": "ATIVO"
    },
    {
        "Nome do Produto": "LUMIFACE LOÇÃO CREMOSA NUTRITIVA E HIDRATANTE KOSMENTAL AEROSSOL",
        "Processo": "25351.363321/2009-17",
        "Nome da Empresa - CNPJ": "KOOSMETICS INDÚSTRIA E COMÉRCIO DE COSMÉTICOS IMPORTAÇÃO E EXPORTAÇÃO LTDA - 05.297.188/0001-03",
        "Número do Registro": "235140005",
        "Situação": "ATIVO",
        "Vencimento": "13/10/2029",
        "link": "https://consultas.anvisa.gov.br/#/cosmeticos/registrados/25351363321200917/?dataInicial=2029-10-13&dataFinal=2029-10-13",
        "Nome da Empresa": "KOOSMETICS INDÚSTRIA E COMÉRCIO DE COSMÉTICOS IMPORTAÇÃO E EXPORTAÇÃO LTDA",
        "Número do CNPJ da Empresa": "05.297.188/0001-03",
        "Categoria": "CREME OU LOÇÃO PARA O ROSTO COM FOTOPROTETOR DA PELE E/ou COM OUTRAS FINALIDADES ALÉM DA HIDRATAÇÃO (PERFUMADOS OU NÃO, INCLUINDO OS GÉIS)",
        "Publicação do Registro": "13/10/2009",
        "Vencimento do Registro": "13/10/2029",
        "Situação do Produto": "ATIVO"
    },
    {
        "Nome do Produto": "PROTETOR SOLAR FPS 60 RED APPLE",
        "Processo": "25351.391005/2009-25",
        "Nome da Empresa - CNPJ": "COSINTER INTERNACIONAL IND E COM COSMETICOS LTDA - 85.080.836/0001-04",
        "Número do Registro": "216760159",
        "Situação": "ATIVO",
        "Vencimento": "13/10/2029",
        "link": "https://consultas.anvisa.gov.br/#/cosmeticos/registrados/25351391005200925/?dataInicial=2029-10-13&dataFinal=2029-10-13",
        "Nome da Empresa": "COSINTER INTERNACIONAL INDÚSTRIA E COMÉRCIO DE COSMÉTICOS LTDA",
        "Número do CNPJ da Empresa": "85.080.836/0001-04",
        "Categoria": "PROTETOR SOLAR",
        "Publicação do Registro": "13/10/2009",
        "Vencimento do Registro": "13/10/2029",
        "Situação do Produto": "ATIVO"
    },
    {
        "Nome do Produto": "PÓ DESCOLORANTE FAST BLOND CONCEPT PROFISSIONAL",
        "Processo": "25351.273825/2009-77",
        "Nome da Empresa - CNPJ": "ESSENCIALLE INDUSTRIA E COMERCIO DE COSMETICOS LTDA - 07.604.482/0001-38",
        "Número do Registro": "248940001",
        "Situação": "ATIVO",
        "Vencimento": "13/10/2029",
        "link": "https://consultas.anvisa.gov.br/#/cosmeticos/registrados/25351273825200977/?dataInicial=2029-10-13&dataFinal=2029-10-13",
        "Nome da Empresa": "ESSENCIALLE INDUSTRIA E COMERCIO DE COSMETICOS LTDA",
        "Número do CNPJ da Empresa": "07.604.482/0001-38",
        "Categoria": "CLAREADOR PARA CABELOS (LÍQUIDO, GEL, CREME OU SÓLIDO)",
        "Publicação do Registro": "13/10/2009",
        "Vencimento do Registro": "13/10/2029",
        "Situação do Produto": "ATIVO"
    },
    {
        "Nome do Produto": "RELAXER PREMIUM CALCIUM TREATMENT SYSTEM - CREME DE RELAXAMENTO CAPILAR NUTRAT",
        "Processo": "25351.421977/2009-30",
        "Nome da Empresa - CNPJ": "PROLAB INDÚSTRIA E COMÉRCIO DE COSMÉTICOS LTDA - 64.988.678/0001-07",
        "Número do Registro": "232410023",
        "Situação": "ATIVO",
        "Vencimento": "13/10/2029",
        "link": "https://consultas.anvisa.gov.br/#/cosmeticos/registrados/25351421977200930/?dataInicial=2029-10-13&dataFinal=2029-10-13",
        "Nome da Empresa": "PROLAB INDÚSTRIA E COMÉRCIO DE COSMÉTICOS LTDA",
        "Número do CNPJ da Empresa": "64.988.678/0001-07",
        "Categoria": "ALISANTE PARA CABELOS - GRAU 2",
        "Publicação do Registro": "13/10/2009",
        "Vencimento do Registro": "13/10/2029",
        "Situação do Produto": "ATIVO"
    },
    {
        "Nome do Produto": "SABONETE ÍNTIMO NATURAL KENDRA",
        "Processo": "25351.305177/2009-06",
        "Nome da Empresa - CNPJ": "NUTRIPHITOS COSMÉTICOS LTDA - 01.682.906/0001-04",
        "Número do Registro": "226090395",
        "Situação": "ATIVO",
        "Vencimento": "13/10/2029",
        "link": "https://consultas.anvisa.gov.br/#/cosmeticos/registrados/25351305177200906/?dataInicial=2029-10-13&dataFinal=2029-10-13",
        "Nome da Empresa": "NUTRIPHITOS COSMÉTICOS LTDA",
        "Número do CNPJ da Empresa": "01.682.906/0001-04",
        "Categoria": "SABONETE DE USO ÍNTIMO",
        "Publicação do Registro": "13/10/2009",
        "Vencimento do Registro": "13/10/2029",
        "Situação do Produto": "ATIVO"
    },
    {
        "Nome do Produto": "SABONETE ÍNTIMO SUAVE KENDRA",
        "Processo": "25351.305127/2009-17",
        "Nome da Empresa - CNPJ": "NUTRIPHITOS COSMÉTICOS LTDA - 01.682.906/0001-04",
        "Número do Registro": "226090394",
        "Situação": "ATIVO",
        "Vencimento": "13/10/2029",
        "link": "https://consultas.anvisa.gov.br/#/cosmeticos/registrados/25351305127200917/?dataInicial=2029-10-13&dataFinal=2029-10-13",
        "Nome da Empresa": "NUTRIPHITOS COSMÉTICOS LTDA",
        "Número do CNPJ da Empresa": "01.682.906/0001-04",
        "Categoria": "SABONETE DE USO ÍNTIMO",
        "Publicação do Registro": "13/10/2009",
        "Vencimento do Registro": "13/10/2029",
        "Situação do Produto": "ATIVO"
    },
    {
        "Nome do Produto": "SHAMPOO NATU HAIR SOS KIDS",
        "Processo": "25351.320261/2014-91",
        "Nome da Empresa - CNPJ": "BIOSENSE INDUSTRIA E COMERCIO DE PRODUTOS DE COSMETICA LTDA - 30.066.989/0001-05",
        "Número do Registro": "213850318",
        "Situação": "ATIVO",
        "Vencimento": "13/10/2029",
        "link": "https://consultas.anvisa.gov.br/#/cosmeticos/registrados/25351320261201491/?dataInicial=2029-10-13&dataFinal=2029-10-13",
        "Nome da Empresa": "BIOSENSE INDUSTRIA E COMERCIO DE PRODUTOS DE COSMETICA LTDA",
        "Número do CNPJ da Empresa": "30.066.989/0001-05",
        "Categoria": "XAMPU/XAMPU CONDICIONADOR INFANTIL - GRAU 2",
        "Publicação do Registro": "13/10/2014",
        "Vencimento do Registro": "13/10/2029",
        "Situação do Produto": "ATIVO"
    }
]