[
    {
        "Nome do Produto": "AMACIHAIR TRADICIONAL CREME DE RELAXAMENTO",
        "Processo": "25351.023445/2022-22",
        "Nome da Empresa - CNPJ": "PHITOTERAPHIA BIOFITOGENIA LABORATORIAL BIOTA LTDA - 00.104.603/0001-33",
        "Número do Registro": "221000823",
        "Situação": "ATIVO",
        "Vencimento": "18/07/2032",
        "link": "https://consultas.anvisa.gov.br/#/cosmeticos/registrados/25351023445202222/?dataInicial=2032-07-18&dataFinal=2032-07-18",
        "Nome da Empresa": "PHITOTERAPHIA BIOFITOGENIA LABORATORIAL BIOTA LTDA",
        "Número do CNPJ da Empresa": "00.104.603/0001-33",
        "Categoria": "ALISANTE PARA CABELOS - GRAU 2",
        "Publicação do Registro": "18/07/2022",
        "Vencimento do Registro": "18/07/2032",
        "Situação do Produto": "ATIVO"
    },
    {
        "Nome do Produto": "D. GEL ANTISSÉPTICO DELFAR",
        "Processo": "25351.535149/2022-70",
        "Nome da Empresa - CNPJ": "HENLAU QUIMICA LTDA - 01.847.902/0001-20",
        "Número do Registro": "227430217",
        "Situação": "ATIVO",
        "Vencimento": "18/07/2032",
        "link": "https://consultas.anvisa.gov.br/#/cosmeticos/registrados/25351535149202270/?dataInicial=2032-07-18&dataFinal=2032-07-18",
        "Nome da Empresa": "HENLAU QUIMICA LTDA",
        "Número do CNPJ da Empresa": "01.847.902/0001-20",
        "Categoria": "GEL ANTISSÉPTICO PARA AS MÃOS - GRAU 2",
        "Publicação do Registro": "18/07/2022",
        "Vencimento do Registro": "18/07/2032",
        "Situação do Produto": "ATIVO"
    },
    {
        "Nome do Produto": "GEL ANTISSÉPTICO PARA HIGIENE DAS MÃOS ASEPLYNE ALOE VERA",
        "Processo": "25351.110365/2022-14",
        "Nome da Empresa - CNPJ": "CIGEL INDUSTRIAL LTDA - 03.773.027/0001-05",
        "Número do Registro": "232400070",
        "Situação": "ATIVO",
        "Vencimento": "18/07/2032",
        "link": "https://consultas.anvisa.gov.br/#/cosmeticos/registrados/25351110365202214/?dataInicial=2032-07-18&dataFinal=2032-07-18",
        "Nome da Empresa": "CIGEL INDUSTRIAL LTDA",
        "Número do CNPJ da Empresa": "03.773.027/0001-05",
        "Categoria": "GEL ANTISSÉPTICO PARA AS MÃOS - GRAU 2",
        "Publicação do Registro": "18/07/2022",
        "Vencimento do Registro": "18/07/2032",
        "Situação do Produto": "ATIVO"
    },
    {
        "Nome do Produto": "GEL ANTISSÉPTICO PARA HIGIENE DAS MÃOS NEUTRO PURE",
        "Processo": "25351.110380/2022-54",
        "Nome da Empresa - CNPJ": "CIGEL INDUSTRIAL LTDA - 03.773.027/0001-05",
        "Número do Registro": "232400071",
        "Situação": "ATIVO",
        "Vencimento": "18/07/2032",
        "link": "https://consultas.anvisa.gov.br/#/cosmeticos/registrados/25351110380202254/?dataInicial=2032-07-18&dataFinal=2032-07-18",
        "Nome da Empresa": "CIGEL INDUSTRIAL LTDA",
        "Número do CNPJ da Empresa": "03.773.027/0001-05",
        "Categoria": "GEL ANTISSÉPTICO PARA AS MÃOS - GRAU 2",
        "Publicação do Registro": "18/07/2022",
        "Vencimento do Registro": "18/07/2032",
        "Situação do Produto": "ATIVO"
    },
    {
        "Nome do Produto": "MIÓ MANTEIGA DE CACAU PROTETOR SOLAR LABIAL FPS 8",
        "Processo": "25351.535155/2022-27",
        "Nome da Empresa - CNPJ": "BRAVIR INDUSTRIAL LTDA - 18.688.481/0001-35",
        "Número do Registro": "206420065",
        "Situação": "ATIVO",
        "Vencimento": "18/07/2032",
        "link": "https://consultas.anvisa.gov.br/#/cosmeticos/registrados/25351535155202227/?dataInicial=2032-07-18&dataFinal=2032-07-18",
        "Nome da Empresa": "BRAVIR INDUSTRIAL LTDA",
        "Número do CNPJ da Empresa": "18.688.481/0001-35",
        "Categoria": "PROTETOR SOLAR - GRAU 2",
        "Publicação do Registro": "18/07/2022",
        "Vencimento do Registro": "18/07/2032",
        "Situação do Produto": "ATIVO"
    },
    {
        "Nome do Produto": "PROTETOR SOLAR CORPO & ROSTO NATIVEG FPS 30",
        "Processo": "25351.028547/2022-34",
        "Nome da Empresa - CNPJ": "OCEAN INDUSTRIA QUIMICA LTDA EPP - 08.158.761/0001-88",
        "Número do Registro": "267460003",
        "Situação": "ATIVO",
        "Vencimento": "18/07/2032",
        "link": "https://consultas.anvisa.gov.br/#/cosmeticos/registrados/25351028547202234/?dataInicial=2032-07-18&dataFinal=2032-07-18",
        "Nome da Empresa": "OCEAN INDUSTRIA QUIMICA LTDA EPP",
        "Número do CNPJ da Empresa": "08.158.761/0001-88",
        "Categoria": "PROTETOR SOLAR - GRAU 2",
        "Publicação do Registro": "18/07/2022",
        "Vencimento do Registro": "18/07/2032",
        "Situação do Produto": "ATIVO"
    },
    {
        "Nome do Produto": "PROTETOR SOLAR FACIAL FPS 70 - HELIODERM DERMOCOSMÉTICOS",
        "Processo": "25351.506247/2022-08",
        "Nome da Empresa - CNPJ": "PASTEUR COSMIATRIA LTDA - 87.727.277/0001-07",
        "Número do Registro": "214850424",
        "Situação": "ATIVO",
        "Vencimento": "18/07/2032",
        "link": "https://consultas.anvisa.gov.br/#/cosmeticos/registrados/25351506247202208/?dataInicial=2032-07-18&dataFinal=2032-07-18",
        "Nome da Empresa": "PASTEUR COSMIATRIA LTDA",
        "Número do CNPJ da Empresa": "87.727.277/0001-07",
        "Categoria": "PROTETOR SOLAR - GRAU 2",
        "Publicação do Registro": "18/07/2022",
        "Vencimento do Registro": "18/07/2032",
        "Situação do Produto": "ATIVO"
    },
    {
        "Nome do Produto": "PROTETOR SOLAR FACIAL PANVEL COR CLARA FPS 70",
        "Processo": "25351.243500/2022-07",
        "Nome da Empresa - CNPJ": "LABORATORIO INDUSTRIAL FARMACÊUTICO LIFAR LTDA - 92.928.951/0001-43",
        "Número do Registro": "238680119",
        "Situação": "ATIVO",
        "Vencimento": "18/07/2032",
        "link": "https://consultas.anvisa.gov.br/#/cosmeticos/registrados/25351243500202207/?dataInicial=2032-07-18&dataFinal=2032-07-18",
        "Nome da Empresa": "LABORATORIO INDUSTRIAL FARMACÊUTICO LIFAR LTDA",
        "Número do CNPJ da Empresa": "92.928.951/0001-43",
        "Categoria": "PROTETOR SOLAR - GRAU 2",
        "Publicação do Registro": "18/07/2022",
        "Vencimento do Registro": "18/07/2032",
        "Situação do Produto": "ATIVO"
    },
    {
        "Nome do Produto": "PROTETOR SOLAR FPS 50 - DERMACHEM LABORATORY",
        "Processo": "25351.525674/2022-87",
        "Nome da Empresa - CNPJ": "PROLINK INDÚSTRIA QUÍMICA LTDA - 01.140.700/0001-44",
        "Número do Registro": "296960005",
        "Situação": "ATIVO",
        "Vencimento": "18/07/2032",
        "link": "https://consultas.anvisa.gov.br/#/cosmeticos/registrados/25351525674202287/?dataInicial=2032-07-18&dataFinal=2032-07-18",
        "Nome da Empresa": "PROLINK INDÚSTRIA QUÍMICA LTDA",
        "Número do CNPJ da Empresa": "01.140.700/0001-44",
        "Categoria": "PROTETOR SOLAR - GRAU 2",
        "Publicação do Registro": "18/07/2022",
        "Vencimento do Registro": "18/07/2032",
        "Situação do Produto": "ATIVO"
    },
    {
        "Nome do Produto": "PROTETOR SOLAR FPS 70 - DERMACHEM LABORATORY",
        "Processo": "25351.525724/2022-26",
        "Nome da Empresa - CNPJ": "PROLINK INDÚSTRIA QUÍMICA LTDA - 01.140.700/0001-44",
        "Número do Registro": "296960006",
        "Situação": "ATIVO",
        "Vencimento": "18/07/2032",
        "link": "https://consultas.anvisa.gov.br/#/cosmeticos/registrados/25351525724202226/?dataInicial=2032-07-18&dataFinal=2032-07-18",
        "Nome da Empresa": "PROLINK INDÚSTRIA QUÍMICA LTDA",
        "Número do CNPJ da Empresa": "01.140.700/0001-44",
        "Categoria": "PROTETOR SOLAR - GRAU 2",
        "Publicação do Registro": "18/07/2022",
        "Vencimento do Registro": "18/07/2032",
        "Situação do Produto": "ATIVO"
    },
    {
        "Nome do Produto": "AMACIHAIR TRADICIONAL CREME DE RELAXAMENTO",
        "Processo": "25351.023445/2022-22",
        "Nome da Empresa - CNPJ": "PHITOTERAPHIA BIOFITOGENIA LABORATORIAL BIOTA LTDA - 00.104.603/0001-33",
        "Número do Registro": "221000823",
        "Situação": "ATIVO",
        "Vencimento": "18/07/2032",
        "link": "https://consultas.anvisa.gov.br/#/cosmeticos/registrados/25351023445202222/?dataInicial=2032-07-18&dataFinal=2032-07-18",
        "Nome da Empresa": "PHITOTERAPHIA BIOFITOGENIA LABORATORIAL BIOTA LTDA",
        "Número do CNPJ da Empresa": "00.104.603/0001-33",
        "Categoria": "ALISANTE PARA CABELOS - GRAU 2",
        "Publicação do Registro": "18/07/2022",
        "Vencimento do Registro": "18/07/2032",
        "Situação do Produto": "ATIVO"
    },
    {
        "Nome do Produto": "D. GEL ANTISSÉPTICO DELFAR",
        "Processo": "25351.535149/2022-70",
        "Nome da Empresa - CNPJ": "HENLAU QUIMICA LTDA - 01.847.902/0001-20",
        "Número do Registro": "227430217",
        "Situação": "ATIVO",
        "Vencimento": "18/07/2032",
        "link": "https://consultas.anvisa.gov.br/#/cosmeticos/registrados/25351535149202270/?dataInicial=2032-07-18&dataFinal=2032-07-18",
        "Nome da Empresa": "HENLAU QUIMICA LTDA",
        "Número do CNPJ da Empresa": "01.847.902/0001-20",
        "Categoria": "GEL ANTISSÉPTICO PARA AS MÃOS - GRAU 2",
        "Publicação do Registro": "18/07/2022",
        "Vencimento do Registro": "18/07/2032",
        "Situação do Produto": "ATIVO"
    },
    {
        "Nome do Produto": "GEL ANTISSÉPTICO PARA HIGIENE DAS MÃOS ASEPLYNE ALOE VERA",
        "Processo": "25351.110365/2022-14",
        "Nome da Empresa - CNPJ": "CIGEL INDUSTRIAL LTDA - 03.773.027/0001-05",
        "Número do Registro": "232400070",
        "Situação": "ATIVO",
        "Vencimento": "18/07/2032",
        "link": "https://consultas.anvisa.gov.br/#/cosmeticos/registrados/25351110365202214/?dataInicial=2032-07-18&dataFinal=2032-07-18",
        "Nome da Empresa": "CIGEL INDUSTRIAL LTDA",
        "Número do CNPJ da Empresa": "03.773.027/0001-05",
        "Categoria": "GEL ANTISSÉPTICO PARA AS MÃOS - GRAU 2",
        "Publicação do Registro": "18/07/2022",
        "Vencimento do Registro": "18/07/2032",
        "Situação do Produto": "ATIVO"
    },
    {
        "Nome do Produto": "GEL ANTISSÉPTICO PARA HIGIENE DAS MÃOS NEUTRO PURE",
        "Processo": "25351.110380/2022-54",
        "Nome da Empresa - CNPJ": "CIGEL INDUSTRIAL LTDA - 03.773.027/0001-05",
        "Número do Registro": "232400071",
        "Situação": "ATIVO",
        "Vencimento": "18/07/2032",
        "link": "https://consultas.anvisa.gov.br/#/cosmeticos/registrados/25351110380202254/?dataInicial=2032-07-18&dataFinal=2032-07-18",
        "Nome da Empresa": "CIGEL INDUSTRIAL LTDA",
        "Número do CNPJ da Empresa": "03.773.027/0001-05",
        "Categoria": "GEL ANTISSÉPTICO PARA AS MÃOS - GRAU 2",
        "Publicação do Registro": "18/07/2022",
        "Vencimento do Registro": "18/07/2032",
        "Situação do Produto": "ATIVO"
    },
    {
        "Nome do Produto": "MIÓ MANTEIGA DE CACAU PROTETOR SOLAR LABIAL FPS 8",
        "Processo": "25351.535155/2022-27",
        "Nome da Empresa - CNPJ": "BRAVIR INDUSTRIAL LTDA - 18.688.481/0001-35",
        "Número do Registro": "206420065",
        "Situação": "ATIVO",
        "Vencimento": "18/07/2032",
        "link": "https://consultas.anvisa.gov.br/#/cosmeticos/registrados/25351535155202227/?dataInicial=2032-07-18&dataFinal=2032-07-18",
        "Nome da Empresa": "BRAVIR INDUSTRIAL LTDA",
        "Número do CNPJ da Empresa": "18.688.481/0001-35",
        "Categoria": "PROTETOR SOLAR - GRAU 2",
        "Publicação do Registro": "18/07/2022",
        "Vencimento do Registro": "18/07/2032",
        "Situação do Produto": "ATIVO"
    },
    {
        "Nome do Produto": "PROTETOR SOLAR CORPO & ROSTO NATIVEG FPS 30",
        "Processo": "25351.028547/2022-34",
        "Nome da Empresa - CNPJ": "OCEAN INDUSTRIA QUIMICA LTDA EPP - 08.158.761/0001-88",
        "Número do Registro": "267460003",
        "Situação": "ATIVO",
        "Vencimento": "18/07/2032",
        "link": "https://consultas.anvisa.gov.br/#/cosmeticos/registrados/25351028547202234/?dataInicial=2032-07-18&dataFinal=2032-07-18",
        "Nome da Empresa": "OCEAN INDUSTRIA QUIMICA LTDA EPP",
        "Número do CNPJ da Empresa": "08.158.761/0001-88",
        "Categoria": "PROTETOR SOLAR - GRAU 2",
        "Publicação do Registro": "18/07/2022",
        "Vencimento do Registro": "18/07/2032",
        "Situação do Produto": "ATIVO"
    },
    {
        "Nome do Produto": "PROTETOR SOLAR FACIAL FPS 70 - HELIODERM DERMOCOSMÉTICOS",
        "Processo": "25351.506247/2022-08",
        "Nome da Empresa - CNPJ": "PASTEUR COSMIATRIA LTDA - 87.727.277/0001-07",
        "Número do Registro": "214850424",
        "Situação": "ATIVO",
        "Vencimento": "18/07/2032",
        "link": "https://consultas.anvisa.gov.br/#/cosmeticos/registrados/25351506247202208/?dataInicial=2032-07-18&dataFinal=2032-07-18",
        "Nome da Empresa": "PASTEUR COSMIATRIA LTDA",
        "Número do CNPJ da Empresa": "87.727.277/0001-07",
        "Categoria": "PROTETOR SOLAR - GRAU 2",
        "Publicação do Registro": "18/07/2022",
        "Vencimento do Registro": "18/07/2032",
        "Situação do Produto": "ATIVO"
    },
    {
        "Nome do Produto": "PROTETOR SOLAR FACIAL PANVEL COR CLARA FPS 70",
        "Processo": "25351.243500/2022-07",
        "Nome da Empresa - CNPJ": "LABORATORIO INDUSTRIAL FARMACÊUTICO LIFAR LTDA - 92.928.951/0001-43",
        "Número do Registro": "238680119",
        "Situação": "ATIVO",
        "Vencimento": "18/07/2032",
        "link": "https://consultas.anvisa.gov.br/#/cosmeticos/registrados/25351243500202207/?dataInicial=2032-07-18&dataFinal=2032-07-18",
        "Nome da Empresa": "LABORATORIO INDUSTRIAL FARMACÊUTICO LIFAR LTDA",
        "Número do CNPJ da Empresa": "92.928.951/0001-43",
        "Categoria": "PROTETOR SOLAR - GRAU 2",
        "Publicação do Registro": "18/07/2022",
        "Vencimento do Registro": "18/07/2032",
        "Situação do Produto": "ATIVO"
    },
    {
        "Nome do Produto": "PROTETOR SOLAR FPS 50 - DERMACHEM LABORATORY",
        "Processo": "25351.525674/2022-87",
        "Nome da Empresa - CNPJ": "PROLINK INDÚSTRIA QUÍMICA LTDA - 01.140.700/0001-44",
        "Número do Registro": "296960005",
        "Situação": "ATIVO",
        "Vencimento": "18/07/2032",
        "link": "https://consultas.anvisa.gov.br/#/cosmeticos/registrados/25351525674202287/?dataInicial=2032-07-18&dataFinal=2032-07-18",
        "Nome da Empresa": "PROLINK INDÚSTRIA QUÍMICA LTDA",
        "Número do CNPJ da Empresa": "01.140.700/0001-44",
        "Categoria": "PROTETOR SOLAR - GRAU 2",
        "Publicação do Registro": "18/07/2022",
        "Vencimento do Registro": "18/07/2032",
        "Situação do Produto": "ATIVO"
    },
    {
        "Nome do Produto": "PROTETOR SOLAR FPS 70 - DERMACHEM LABORATORY",
        "Processo": "25351.525724/2022-26",
        "Nome da Empresa - CNPJ": "PROLINK INDÚSTRIA QUÍMICA LTDA - 01.140.700/0001-44",
        "Número do Registro": "296960006",
        "Situação": "ATIVO",
        "Vencimento": "18/07/2032",
        "link": "https://consultas.anvisa.gov.br/#/cosmeticos/registrados/25351525724202226/?dataInicial=2032-07-18&dataFinal=2032-07-18",
        "Nome da Empresa": "PROLINK INDÚSTRIA QUÍMICA LTDA",
        "Número do CNPJ da Empresa": "01.140.700/0001-44",
        "Categoria": "PROTETOR SOLAR - GRAU 2",
        "Publicação do Registro": "18/07/2022",
        "Vencimento do Registro": "18/07/2032",
        "Situação do Produto": "ATIVO"
    },
    {
        "Nome do Produto": "PROTETOR SOLAR FPS 70 - HELIODERM DERMOCOSMÉTICO",
        "Processo": "25351.506227/2022-29",
        "Nome da Empresa - CNPJ": "PASTEUR COSMIATRIA LTDA - 87.727.277/0001-07",
        "Número do Registro": "214850425",
        "Situação": "ATIVO",
        "Vencimento": "18/07/2032",
        "link": "https://consultas.anvisa.gov.br/#/cosmeticos/registrados/25351506227202229/?dataInicial=2032-07-18&dataFinal=2032-07-18",
        "Nome da Empresa": "PASTEUR COSMIATRIA LTDA",
        "Número do CNPJ da Empresa": "87.727.277/0001-07",
        "Categoria": "PROTETOR SOLAR - GRAU 2",
        "Publicação do Registro": "18/07/2022",
        "Vencimento do Registro": "18/07/2032",
        "Situação do Produto": "ATIVO"
    },
    {
        "Nome do Produto": "ÁLCOOL GEL ANTISSÉPTICO PARA AS MÃOS ERVA DOCE /SALUTARIS",
        "Processo": "25351.125260/2021-71",
        "Nome da Empresa - CNPJ": "SALUTARIS INDÚSTRIA DE COSMÉTICOS LTDA - 07.421.681/0001-00",
        "Número do Registro": "252640068",
        "Situação": "ATIVO",
        "Vencimento": "18/07/2032",
        "link": "https://consultas.anvisa.gov.br/#/cosmeticos/registrados/25351125260202171/?dataInicial=2032-07-18&dataFinal=2032-07-18",
        "Nome da Empresa": "SALUTARIS INDÚSTRIA DE COSMÉTICOS LTDA",
        "Número do CNPJ da Empresa": "07.421.681/0001-00",
        "Categoria": "GEL ANTISSÉPTICO PARA AS MÃOS - GRAU 2",
        "Publicação do Registro": "18/07/2022",
        "Vencimento do Registro": "18/07/2032",
        "Situação do Produto": "ATIVO"
    }
]