[
    {
        "Nome do Produto": "ALFAPARF EVOLUTION OF THE COLOR CUBE COLORACIÓN COSMÉTICA PERMANENTE",
        "Processo": "25351.707380/2011-92",
        "Nome da Empresa - CNPJ": "DELLY KOSMETIC COMÉRCIO E INDÚSTRIA LTDA - 01.567.613/0001-78",
        "Número do Registro": "225600253",
        "Situação": "ATIVO",
        "Vencimento": "23/01/2027",
        "link": "https://consultas.anvisa.gov.br/#/cosmeticos/registrados/25351707380201192/?dataInicial=2027-01-23&dataFinal=2027-01-23",
        "Nome da Empresa": "DELLY KOSMETIC COMÉRCIO E INDÚSTRIA LTDA",
        "Número do CNPJ da Empresa": "01.567.613/0001-78",
        "Categoria": "TINTURA PERMANENTE (LÍQUIDO, GEL, CREME OU SÓLIDO)",
        "Publicação do Registro": "23/01/2012",
        "Vencimento do Registro": "23/01/2027",
        "Situação do Produto": "ATIVO"
    },
    {
        "Nome do Produto": "ANTIMOSQUITOS ISDIN REPELENTE DE INSETOS INFANTIL DE ALTA EFICACIA SPRAY",
        "Processo": "25351.288043/2016-39",
        "Nome da Empresa - CNPJ": "Isdin Produtos Farmaceuticos Ltda - 10.817.114/0001-82",
        "Número do Registro": "253860039",
        "Situação": "INATIVO",
        "Vencimento": "23/01/2027",
        "link": "https://consultas.anvisa.gov.br/#/cosmeticos/registrados/25351288043201639/?dataInicial=2027-01-23&dataFinal=2027-01-23",
        "Nome da Empresa": "Isdin Produtos Farmaceuticos Ltda",
        "Número do CNPJ da Empresa": "10.817.114/0001-82",
        "Categoria": "REPELENTE DE INSETOS INFANTIL - GRAU 2",
        "Publicação do Registro": "23/01/2017",
        "Vencimento do Registro": "23/01/2027",
        "Situação do Produto": "INATIVO"
    },
    {
        "Nome do Produto": "AVON TRUE HIDRATANTE PROTETOR CREME FACIAL HIDRATAÇÃO INTENSA FPS 15",
        "Processo": "25351.325284/2016-95",
        "Nome da Empresa - CNPJ": "AVON INDUSTRIAL LTDA - 00.680.516/0001-24",
        "Número do Registro": "200042131",
        "Situação": "INATIVO",
        "Vencimento": "23/01/2027",
        "link": "https://consultas.anvisa.gov.br/#/cosmeticos/registrados/25351325284201695/?dataInicial=2027-01-23&dataFinal=2027-01-23",
        "Nome da Empresa": "AVON INDUSTRIAL LTDA",
        "Número do CNPJ da Empresa": "00.680.516/0001-24",
        "Categoria": "PROTETOR SOLAR - GRAU 2",
        "Publicação do Registro": "23/01/2017",
        "Vencimento do Registro": "23/01/2027",
        "Situação do Produto": "INATIVO"
    },
    {
        "Nome do Produto": "BABY WIPES ALL PURPOSE HORA DO SONO PARENT'S CHOICE",
        "Processo": "25351.372311/2016-48",
        "Nome da Empresa - CNPJ": "LENÇOBRÁS INDÚSTRIA E COMÉRCIO DE LENÇOS UMEDECIDOS LTDA - 05.756.446/0001-64",
        "Número do Registro": "237550057",
        "Situação": "INATIVO",
        "Vencimento": "23/01/2027",
        "link": "https://consultas.anvisa.gov.br/#/cosmeticos/registrados/25351372311201648/?dataInicial=2027-01-23&dataFinal=2027-01-23",
        "Nome da Empresa": "LENÇOBRÁS INDÚSTRIA E COMÉRCIO DE LENÇOS UMEDECIDOS LTDA",
        "Número do CNPJ da Empresa": "05.756.446/0001-64",
        "Categoria": "PRODUTO DE LIMPEZA/HIGIENIZAÇÃO INFANTIL - GRAU 2",
        "Publicação do Registro": "23/01/2017",
        "Vencimento do Registro": "23/01/2027",
        "Situação do Produto": "INATIVO"
    },
    {
        "Nome do Produto": "BABY WIPES ALL PURPOSE MULTIUSO PARENT'S CHOICE",
        "Processo": "25351.372315/2016-54",
        "Nome da Empresa - CNPJ": "LENÇOBRÁS INDÚSTRIA E COMÉRCIO DE LENÇOS UMEDECIDOS LTDA - 05.756.446/0001-64",
        "Número do Registro": "237550059",
        "Situação": "INATIVO",
        "Vencimento": "23/01/2027",
        "link": "https://consultas.anvisa.gov.br/#/cosmeticos/registrados/25351372315201654/?dataInicial=2027-01-23&dataFinal=2027-01-23",
        "Nome da Empresa": "LENÇOBRÁS INDÚSTRIA E COMÉRCIO DE LENÇOS UMEDECIDOS LTDA",
        "Número do CNPJ da Empresa": "05.756.446/0001-64",
        "Categoria": "PRODUTO DE LIMPEZA/HIGIENIZAÇÃO INFANTIL - GRAU 2",
        "Publicação do Registro": "23/01/2017",
        "Vencimento do Registro": "23/01/2027",
        "Situação do Produto": "INATIVO"
    },
    {
        "Nome do Produto": "COLONIA CHUÁ CHUÁ DORA A AVENTUREIRA",
        "Processo": "25351.314013/2016-27",
        "Nome da Empresa - CNPJ": "ATHENAS INDÚSTRIA E TERCERIZAÇÃO DE COSMÉTICOS LTDA EPP - 01.287.021/0001-00",
        "Número do Registro": "266700082",
        "Situação": "INATIVO",
        "Vencimento": "23/01/2027",
        "link": "https://consultas.anvisa.gov.br/#/cosmeticos/registrados/25351314013201627/?dataInicial=2027-01-23&dataFinal=2027-01-23",
        "Nome da Empresa": "ATHENAS INDÚSTRIA E TERCERIZAÇÃO DE COSMÉTICOS LTDA EPP",
        "Número do CNPJ da Empresa": "01.287.021/0001-00",
        "Categoria": "COLÔNIAS INFANTIS (HIDROALCOÓLICAS OU NÃO)",
        "Publicação do Registro": "23/01/2017",
        "Vencimento do Registro": "23/01/2027",
        "Situação do Produto": "INATIVO"
    },
    {
        "Nome do Produto": "CREMA ALISANTE FUERTE CHEMDY BELL",
        "Processo": "25351.533355/2011-10",
        "Nome da Empresa - CNPJ": "KAKÁ DISTRIBUIDORA DE COSMÉTICOS LTDA. - 03.804.767/0001-61",
        "Número do Registro": "252570001",
        "Situação": "INATIVO",
        "Vencimento": "23/01/2027",
        "link": "https://consultas.anvisa.gov.br/#/cosmeticos/registrados/25351533355201110/?dataInicial=2027-01-23&dataFinal=2027-01-23",
        "Nome da Empresa": "KAKÁ DISTRIBUIDORA DE COSMÉTICOS LTDA.",
        "Número do CNPJ da Empresa": "03.804.767/0001-61",
        "Categoria": "ALISANTE PARA CABELOS (CREME OU GEL)",
        "Publicação do Registro": "23/01/2012",
        "Vencimento do Registro": "23/01/2027",
        "Situação do Produto": "INATIVO"
    },
    {
        "Nome do Produto": "CREME ALISA E TINGE PARA ALISAMENTO OU RELAXAMENTO AROMA DO CAMPO",
        "Processo": "25351.325099/2016-23",
        "Nome da Empresa - CNPJ": "IMS-COMERCIAL E INDUSTRIAL LTDA - 31.069.347/0001-14",
        "Número do Registro": "214360716",
        "Situação": "INATIVO",
        "Vencimento": "23/01/2027",
        "link": "https://consultas.anvisa.gov.br/#/cosmeticos/registrados/25351325099201623/?dataInicial=2027-01-23&dataFinal=2027-01-23",
        "Nome da Empresa": "IMS COMERCIAL E INDUSTRIAL LTDA",
        "Número do CNPJ da Empresa": "31.069.347/0001-14",
        "Categoria": "ALISANTE PARA CABELOS - GRAU 2",
        "Publicação do Registro": "23/01/2017",
        "Vencimento do Registro": "23/01/2027",
        "Situação do Produto": "INATIVO"
    },
    {
        "Nome do Produto": "CREME RELAXANTE 1 - EXTRAFORTE - AFRONATURE",
        "Processo": "25351.044822/2016-18",
        "Nome da Empresa - CNPJ": "ATSUM INDÚSTRIA E COMÉRCIO DE COSMÉTICOS LTDA - 06.215.185/0001-38",
        "Número do Registro": "240880099",
        "Situação": "INATIVO",
        "Vencimento": "23/01/2027",
        "link": "https://consultas.anvisa.gov.br/#/cosmeticos/registrados/25351044822201618/?dataInicial=2027-01-23&dataFinal=2027-01-23",
        "Nome da Empresa": "ATSUM INDÚSTRIA E COMÉRCIO DE COSMÉTICOS LTDA",
        "Número do CNPJ da Empresa": "06.215.185/0001-38",
        "Categoria": "ALISANTE PARA CABELOS - GRAU 2",
        "Publicação do Registro": "23/01/2017",
        "Vencimento do Registro": "23/01/2027",
        "Situação do Produto": "INATIVO"
    },
    {
        "Nome do Produto": "CREME RELAXANTE 2 - FORTE - AFRONATURE",
        "Processo": "25351.044800/2016-26",
        "Nome da Empresa - CNPJ": "ATSUM INDÚSTRIA E COMÉRCIO DE COSMÉTICOS LTDA - 06.215.185/0001-38",
        "Número do Registro": "240880098",
        "Situação": "INATIVO",
        "Vencimento": "23/01/2027",
        "link": "https://consultas.anvisa.gov.br/#/cosmeticos/registrados/25351044800201626/?dataInicial=2027-01-23&dataFinal=2027-01-23",
        "Nome da Empresa": "ATSUM INDÚSTRIA E COMÉRCIO DE COSMÉTICOS LTDA",
        "Número do CNPJ da Empresa": "06.215.185/0001-38",
        "Categoria": "ALISANTE PARA CABELOS - GRAU 2",
        "Publicação do Registro": "23/01/2017",
        "Vencimento do Registro": "23/01/2027",
        "Situação do Produto": "INATIVO"
    },
    {
        "Nome do Produto": "ALFAPARF EVOLUTION OF THE COLOR CUBE COLORACIÓN COSMÉTICA PERMANENTE",
        "Processo": "25351.707380/2011-92",
        "Nome da Empresa - CNPJ": "DELLY KOSMETIC COMÉRCIO E INDÚSTRIA LTDA - 01.567.613/0001-78",
        "Número do Registro": "225600253",
        "Situação": "ATIVO",
        "Vencimento": "23/01/2027",
        "link": "https://consultas.anvisa.gov.br/#/cosmeticos/registrados/25351707380201192/?dataInicial=2027-01-23&dataFinal=2027-01-23",
        "Nome da Empresa": "DELLY KOSMETIC COMÉRCIO E INDÚSTRIA LTDA",
        "Número do CNPJ da Empresa": "01.567.613/0001-78",
        "Categoria": "TINTURA PERMANENTE (LÍQUIDO, GEL, CREME OU SÓLIDO)",
        "Publicação do Registro": "23/01/2012",
        "Vencimento do Registro": "23/01/2027",
        "Situação do Produto": "ATIVO"
    },
    {
        "Nome do Produto": "ANTIMOSQUITOS ISDIN REPELENTE DE INSETOS INFANTIL DE ALTA EFICACIA SPRAY",
        "Processo": "25351.288043/2016-39",
        "Nome da Empresa - CNPJ": "Isdin Produtos Farmaceuticos Ltda - 10.817.114/0001-82",
        "Número do Registro": "253860039",
        "Situação": "INATIVO",
        "Vencimento": "23/01/2027",
        "link": "https://consultas.anvisa.gov.br/#/cosmeticos/registrados/25351288043201639/?dataInicial=2027-01-23&dataFinal=2027-01-23",
        "Nome da Empresa": "Isdin Produtos Farmaceuticos Ltda",
        "Número do CNPJ da Empresa": "10.817.114/0001-82",
        "Categoria": "REPELENTE DE INSETOS INFANTIL - GRAU 2",
        "Publicação do Registro": "23/01/2017",
        "Vencimento do Registro": "23/01/2027",
        "Situação do Produto": "INATIVO"
    },
    {
        "Nome do Produto": "AVON TRUE HIDRATANTE PROTETOR CREME FACIAL HIDRATAÇÃO INTENSA FPS 15",
        "Processo": "25351.325284/2016-95",
        "Nome da Empresa - CNPJ": "AVON INDUSTRIAL LTDA - 00.680.516/0001-24",
        "Número do Registro": "200042131",
        "Situação": "INATIVO",
        "Vencimento": "23/01/2027",
        "link": "https://consultas.anvisa.gov.br/#/cosmeticos/registrados/25351325284201695/?dataInicial=2027-01-23&dataFinal=2027-01-23",
        "Nome da Empresa": "AVON INDUSTRIAL LTDA",
        "Número do CNPJ da Empresa": "00.680.516/0001-24",
        "Categoria": "PROTETOR SOLAR - GRAU 2",
        "Publicação do Registro": "23/01/2017",
        "Vencimento do Registro": "23/01/2027",
        "Situação do Produto": "INATIVO"
    },
    {
        "Nome do Produto": "BABY WIPES ALL PURPOSE HORA DO SONO PARENT'S CHOICE",
        "Processo": "25351.372311/2016-48",
        "Nome da Empresa - CNPJ": "LENÇOBRÁS INDÚSTRIA E COMÉRCIO DE LENÇOS UMEDECIDOS LTDA - 05.756.446/0001-64",
        "Número do Registro": "237550057",
        "Situação": "INATIVO",
        "Vencimento": "23/01/2027",
        "link": "https://consultas.anvisa.gov.br/#/cosmeticos/registrados/25351372311201648/?dataInicial=2027-01-23&dataFinal=2027-01-23",
        "Nome da Empresa": "LENÇOBRÁS INDÚSTRIA E COMÉRCIO DE LENÇOS UMEDECIDOS LTDA",
        "Número do CNPJ da Empresa": "05.756.446/0001-64",
        "Categoria": "PRODUTO DE LIMPEZA/HIGIENIZAÇÃO INFANTIL - GRAU 2",
        "Publicação do Registro": "23/01/2017",
        "Vencimento do Registro": "23/01/2027",
        "Situação do Produto": "INATIVO"
    },
    {
        "Nome do Produto": "BABY WIPES ALL PURPOSE MULTIUSO PARENT'S CHOICE",
        "Processo": "25351.372315/2016-54",
        "Nome da Empresa - CNPJ": "LENÇOBRÁS INDÚSTRIA E COMÉRCIO DE LENÇOS UMEDECIDOS LTDA - 05.756.446/0001-64",
        "Número do Registro": "237550059",
        "Situação": "INATIVO",
        "Vencimento": "23/01/2027",
        "link": "https://consultas.anvisa.gov.br/#/cosmeticos/registrados/25351372315201654/?dataInicial=2027-01-23&dataFinal=2027-01-23",
        "Nome da Empresa": "LENÇOBRÁS INDÚSTRIA E COMÉRCIO DE LENÇOS UMEDECIDOS LTDA",
        "Número do CNPJ da Empresa": "05.756.446/0001-64",
        "Categoria": "PRODUTO DE LIMPEZA/HIGIENIZAÇÃO INFANTIL - GRAU 2",
        "Publicação do Registro": "23/01/2017",
        "Vencimento do Registro": "23/01/2027",
        "Situação do Produto": "INATIVO"
    },
    {
        "Nome do Produto": "COLONIA CHUÁ CHUÁ DORA A AVENTUREIRA",
        "Processo": "25351.314013/2016-27",
        "Nome da Empresa - CNPJ": "ATHENAS INDÚSTRIA E TERCERIZAÇÃO DE COSMÉTICOS LTDA EPP - 01.287.021/0001-00",
        "Número do Registro": "266700082",
        "Situação": "INATIVO",
        "Vencimento": "23/01/2027",
        "link": "https://consultas.anvisa.gov.br/#/cosmeticos/registrados/25351314013201627/?dataInicial=2027-01-23&dataFinal=2027-01-23",
        "Nome da Empresa": "ATHENAS INDÚSTRIA E TERCERIZAÇÃO DE COSMÉTICOS LTDA EPP",
        "Número do CNPJ da Empresa": "01.287.021/0001-00",
        "Categoria": "COLÔNIAS INFANTIS (HIDROALCOÓLICAS OU NÃO)",
        "Publicação do Registro": "23/01/2017",
        "Vencimento do Registro": "23/01/2027",
        "Situação do Produto": "INATIVO"
    },
    {
        "Nome do Produto": "CREMA ALISANTE FUERTE CHEMDY BELL",
        "Processo": "25351.533355/2011-10",
        "Nome da Empresa - CNPJ": "KAKÁ DISTRIBUIDORA DE COSMÉTICOS LTDA. - 03.804.767/0001-61",
        "Número do Registro": "252570001",
        "Situação": "INATIVO",
        "Vencimento": "23/01/2027",
        "link": "https://consultas.anvisa.gov.br/#/cosmeticos/registrados/25351533355201110/?dataInicial=2027-01-23&dataFinal=2027-01-23",
        "Nome da Empresa": "KAKÁ DISTRIBUIDORA DE COSMÉTICOS LTDA.",
        "Número do CNPJ da Empresa": "03.804.767/0001-61",
        "Categoria": "ALISANTE PARA CABELOS (CREME OU GEL)",
        "Publicação do Registro": "23/01/2012",
        "Vencimento do Registro": "23/01/2027",
        "Situação do Produto": "INATIVO"
    },
    {
        "Nome do Produto": "CREME ALISA E TINGE PARA ALISAMENTO OU RELAXAMENTO AROMA DO CAMPO",
        "Processo": "25351.325099/2016-23",
        "Nome da Empresa - CNPJ": "IMS-COMERCIAL E INDUSTRIAL LTDA - 31.069.347/0001-14",
        "Número do Registro": "214360716",
        "Situação": "INATIVO",
        "Vencimento": "23/01/2027",
        "link": "https://consultas.anvisa.gov.br/#/cosmeticos/registrados/25351325099201623/?dataInicial=2027-01-23&dataFinal=2027-01-23",
        "Nome da Empresa": "IMS COMERCIAL E INDUSTRIAL LTDA",
        "Número do CNPJ da Empresa": "31.069.347/0001-14",
        "Categoria": "ALISANTE PARA CABELOS - GRAU 2",
        "Publicação do Registro": "23/01/2017",
        "Vencimento do Registro": "23/01/2027",
        "Situação do Produto": "INATIVO"
    },
    {
        "Nome do Produto": "CREME RELAXANTE 1 - EXTRAFORTE - AFRONATURE",
        "Processo": "25351.044822/2016-18",
        "Nome da Empresa - CNPJ": "ATSUM INDÚSTRIA E COMÉRCIO DE COSMÉTICOS LTDA - 06.215.185/0001-38",
        "Número do Registro": "240880099",
        "Situação": "INATIVO",
        "Vencimento": "23/01/2027",
        "link": "https://consultas.anvisa.gov.br/#/cosmeticos/registrados/25351044822201618/?dataInicial=2027-01-23&dataFinal=2027-01-23",
        "Nome da Empresa": "ATSUM INDÚSTRIA E COMÉRCIO DE COSMÉTICOS LTDA",
        "Número do CNPJ da Empresa": "06.215.185/0001-38",
        "Categoria": "ALISANTE PARA CABELOS - GRAU 2",
        "Publicação do Registro": "23/01/2017",
        "Vencimento do Registro": "23/01/2027",
        "Situação do Produto": "INATIVO"
    },
    {
        "Nome do Produto": "CREME RELAXANTE 2 - FORTE - AFRONATURE",
        "Processo": "25351.044800/2016-26",
        "Nome da Empresa - CNPJ": "ATSUM INDÚSTRIA E COMÉRCIO DE COSMÉTICOS LTDA - 06.215.185/0001-38",
        "Número do Registro": "240880098",
        "Situação": "INATIVO",
        "Vencimento": "23/01/2027",
        "link": "https://consultas.anvisa.gov.br/#/cosmeticos/registrados/25351044800201626/?dataInicial=2027-01-23&dataFinal=2027-01-23",
        "Nome da Empresa": "ATSUM INDÚSTRIA E COMÉRCIO DE COSMÉTICOS LTDA",
        "Número do CNPJ da Empresa": "06.215.185/0001-38",
        "Categoria": "ALISANTE PARA CABELOS - GRAU 2",
        "Publicação do Registro": "23/01/2017",
        "Vencimento do Registro": "23/01/2027",
        "Situação do Produto": "INATIVO"
    },
    {
        "Nome do Produto": "ALFAPARF EVOLUTION OF THE COLOR CUBE COLORACIÓN COSMÉTICA PERMANENTE",
        "Processo": "25351.707380/2011-92",
        "Nome da Empresa - CNPJ": "DELLY KOSMETIC COMÉRCIO E INDÚSTRIA LTDA - 01.567.613/0001-78",
        "Número do Registro": "225600253",
        "Situação": "ATIVO",
        "Vencimento": "23/01/2027",
        "link": "https://consultas.anvisa.gov.br/#/cosmeticos/registrados/25351707380201192/?dataInicial=2027-01-23&dataFinal=2027-01-23",
        "Nome da Empresa": "DELLY KOSMETIC COMÉRCIO E INDÚSTRIA LTDA",
        "Número do CNPJ da Empresa": "01.567.613/0001-78",
        "Categoria": "TINTURA PERMANENTE (LÍQUIDO, GEL, CREME OU SÓLIDO)",
        "Publicação do Registro": "23/01/2012",
        "Vencimento do Registro": "23/01/2027",
        "Situação do Produto": "ATIVO"
    },
    {
        "Nome do Produto": "ANTIMOSQUITOS ISDIN REPELENTE DE INSETOS INFANTIL DE ALTA EFICACIA SPRAY",
        "Processo": "25351.288043/2016-39",
        "Nome da Empresa - CNPJ": "Isdin Produtos Farmaceuticos Ltda - 10.817.114/0001-82",
        "Número do Registro": "253860039",
        "Situação": "INATIVO",
        "Vencimento": "23/01/2027",
        "link": "https://consultas.anvisa.gov.br/#/cosmeticos/registrados/25351288043201639/?dataInicial=2027-01-23&dataFinal=2027-01-23",
        "Nome da Empresa": "Isdin Produtos Farmaceuticos Ltda",
        "Número do CNPJ da Empresa": "10.817.114/0001-82",
        "Categoria": "REPELENTE DE INSETOS INFANTIL - GRAU 2",
        "Publicação do Registro": "23/01/2017",
        "Vencimento do Registro": "23/01/2027",
        "Situação do Produto": "INATIVO"
    },
    {
        "Nome do Produto": "AVON TRUE HIDRATANTE PROTETOR CREME FACIAL HIDRATAÇÃO INTENSA FPS 15",
        "Processo": "25351.325284/2016-95",
        "Nome da Empresa - CNPJ": "AVON INDUSTRIAL LTDA - 00.680.516/0001-24",
        "Número do Registro": "200042131",
        "Situação": "INATIVO",
        "Vencimento": "23/01/2027",
        "link": "https://consultas.anvisa.gov.br/#/cosmeticos/registrados/25351325284201695/?dataInicial=2027-01-23&dataFinal=2027-01-23",
        "Nome da Empresa": "AVON INDUSTRIAL LTDA",
        "Número do CNPJ da Empresa": "00.680.516/0001-24",
        "Categoria": "PROTETOR SOLAR - GRAU 2",
        "Publicação do Registro": "23/01/2017",
        "Vencimento do Registro": "23/01/2027",
        "Situação do Produto": "INATIVO"
    },
    {
        "Nome do Produto": "BABY WIPES ALL PURPOSE HORA DO SONO PARENT'S CHOICE",
        "Processo": "25351.372311/2016-48",
        "Nome da Empresa - CNPJ": "LENÇOBRÁS INDÚSTRIA E COMÉRCIO DE LENÇOS UMEDECIDOS LTDA - 05.756.446/0001-64",
        "Número do Registro": "237550057",
        "Situação": "INATIVO",
        "Vencimento": "23/01/2027",
        "link": "https://consultas.anvisa.gov.br/#/cosmeticos/registrados/25351372311201648/?dataInicial=2027-01-23&dataFinal=2027-01-23",
        "Nome da Empresa": "LENÇOBRÁS INDÚSTRIA E COMÉRCIO DE LENÇOS UMEDECIDOS LTDA",
        "Número do CNPJ da Empresa": "05.756.446/0001-64",
        "Categoria": "PRODUTO DE LIMPEZA/HIGIENIZAÇÃO INFANTIL - GRAU 2",
        "Publicação do Registro": "23/01/2017",
        "Vencimento do Registro": "23/01/2027",
        "Situação do Produto": "INATIVO"
    },
    {
        "Nome do Produto": "BABY WIPES ALL PURPOSE MULTIUSO PARENT'S CHOICE",
        "Processo": "25351.372315/2016-54",
        "Nome da Empresa - CNPJ": "LENÇOBRÁS INDÚSTRIA E COMÉRCIO DE LENÇOS UMEDECIDOS LTDA - 05.756.446/0001-64",
        "Número do Registro": "237550059",
        "Situação": "INATIVO",
        "Vencimento": "23/01/2027",
        "link": "https://consultas.anvisa.gov.br/#/cosmeticos/registrados/25351372315201654/?dataInicial=2027-01-23&dataFinal=2027-01-23",
        "Nome da Empresa": "LENÇOBRÁS INDÚSTRIA E COMÉRCIO DE LENÇOS UMEDECIDOS LTDA",
        "Número do CNPJ da Empresa": "05.756.446/0001-64",
        "Categoria": "PRODUTO DE LIMPEZA/HIGIENIZAÇÃO INFANTIL - GRAU 2",
        "Publicação do Registro": "23/01/2017",
        "Vencimento do Registro": "23/01/2027",
        "Situação do Produto": "INATIVO"
    },
    {
        "Nome do Produto": "COLONIA CHUÁ CHUÁ DORA A AVENTUREIRA",
        "Processo": "25351.314013/2016-27",
        "Nome da Empresa - CNPJ": "ATHENAS INDÚSTRIA E TERCERIZAÇÃO DE COSMÉTICOS LTDA EPP - 01.287.021/0001-00",
        "Número do Registro": "266700082",
        "Situação": "INATIVO",
        "Vencimento": "23/01/2027",
        "link": "https://consultas.anvisa.gov.br/#/cosmeticos/registrados/25351314013201627/?dataInicial=2027-01-23&dataFinal=2027-01-23",
        "Nome da Empresa": "ATHENAS INDÚSTRIA E TERCERIZAÇÃO DE COSMÉTICOS LTDA EPP",
        "Número do CNPJ da Empresa": "01.287.021/0001-00",
        "Categoria": "COLÔNIAS INFANTIS (HIDROALCOÓLICAS OU NÃO)",
        "Publicação do Registro": "23/01/2017",
        "Vencimento do Registro": "23/01/2027",
        "Situação do Produto": "INATIVO"
    },
    {
        "Nome do Produto": "CREMA ALISANTE FUERTE CHEMDY BELL",
        "Processo": "25351.533355/2011-10",
        "Nome da Empresa - CNPJ": "KAKÁ DISTRIBUIDORA DE COSMÉTICOS LTDA. - 03.804.767/0001-61",
        "Número do Registro": "252570001",
        "Situação": "INATIVO",
        "Vencimento": "23/01/2027",
        "link": "https://consultas.anvisa.gov.br/#/cosmeticos/registrados/25351533355201110/?dataInicial=2027-01-23&dataFinal=2027-01-23",
        "Nome da Empresa": "KAKÁ DISTRIBUIDORA DE COSMÉTICOS LTDA.",
        "Número do CNPJ da Empresa": "03.804.767/0001-61",
        "Categoria": "ALISANTE PARA CABELOS (CREME OU GEL)",
        "Publicação do Registro": "23/01/2012",
        "Vencimento do Registro": "23/01/2027",
        "Situação do Produto": "INATIVO"
    },
    {
        "Nome do Produto": "CREME ALISA E TINGE PARA ALISAMENTO OU RELAXAMENTO AROMA DO CAMPO",
        "Processo": "25351.325099/2016-23",
        "Nome da Empresa - CNPJ": "IMS-COMERCIAL E INDUSTRIAL LTDA - 31.069.347/0001-14",
        "Número do Registro": "214360716",
        "Situação": "INATIVO",
        "Vencimento": "23/01/2027",
        "link": "https://consultas.anvisa.gov.br/#/cosmeticos/registrados/25351325099201623/?dataInicial=2027-01-23&dataFinal=2027-01-23",
        "Nome da Empresa": "IMS COMERCIAL E INDUSTRIAL LTDA",
        "Número do CNPJ da Empresa": "31.069.347/0001-14",
        "Categoria": "ALISANTE PARA CABELOS - GRAU 2",
        "Publicação do Registro": "23/01/2017",
        "Vencimento do Registro": "23/01/2027",
        "Situação do Produto": "INATIVO"
    },
    {
        "Nome do Produto": "CREME RELAXANTE 1 - EXTRAFORTE - AFRONATURE",
        "Processo": "25351.044822/2016-18",
        "Nome da Empresa - CNPJ": "ATSUM INDÚSTRIA E COMÉRCIO DE COSMÉTICOS LTDA - 06.215.185/0001-38",
        "Número do Registro": "240880099",
        "Situação": "INATIVO",
        "Vencimento": "23/01/2027",
        "link": "https://consultas.anvisa.gov.br/#/cosmeticos/registrados/25351044822201618/?dataInicial=2027-01-23&dataFinal=2027-01-23",
        "Nome da Empresa": "ATSUM INDÚSTRIA E COMÉRCIO DE COSMÉTICOS LTDA",
        "Número do CNPJ da Empresa": "06.215.185/0001-38",
        "Categoria": "ALISANTE PARA CABELOS - GRAU 2",
        "Publicação do Registro": "23/01/2017",
        "Vencimento do Registro": "23/01/2027",
        "Situação do Produto": "INATIVO"
    },
    {
        "Nome do Produto": "CREME RELAXANTE 2 - FORTE - AFRONATURE",
        "Processo": "25351.044800/2016-26",
        "Nome da Empresa - CNPJ": "ATSUM INDÚSTRIA E COMÉRCIO DE COSMÉTICOS LTDA - 06.215.185/0001-38",
        "Número do Registro": "240880098",
        "Situação": "INATIVO",
        "Vencimento": "23/01/2027",
        "link": "https://consultas.anvisa.gov.br/#/cosmeticos/registrados/25351044800201626/?dataInicial=2027-01-23&dataFinal=2027-01-23",
        "Nome da Empresa": "ATSUM INDÚSTRIA E COMÉRCIO DE COSMÉTICOS LTDA",
        "Número do CNPJ da Empresa": "06.215.185/0001-38",
        "Categoria": "ALISANTE PARA CABELOS - GRAU 2",
        "Publicação do Registro": "23/01/2017",
        "Vencimento do Registro": "23/01/2027",
        "Situação do Produto": "INATIVO"
    },
    {
        "Nome do Produto": "CREME RELAXANTE 3 - NORMAL- AFRONATURE",
        "Processo": "25351.044792/2016-36",
        "Nome da Empresa - CNPJ": "ATSUM INDÚSTRIA E COMÉRCIO DE COSMÉTICOS LTDA - 06.215.185/0001-38",
        "Número do Registro": "240880097",
        "Situação": "INATIVO",
        "Vencimento": "23/01/2027",
        "link": "https://consultas.anvisa.gov.br/#/cosmeticos/registrados/25351044792201636/?dataInicial=2027-01-23&dataFinal=2027-01-23",
        "Nome da Empresa": "ATSUM INDÚSTRIA E COMÉRCIO DE COSMÉTICOS LTDA",
        "Número do CNPJ da Empresa": "06.215.185/0001-38",
        "Categoria": "ALISANTE PARA CABELOS - GRAU 2",
        "Publicação do Registro": "23/01/2017",
        "Vencimento do Registro": "23/01/2027",
        "Situação do Produto": "INATIVO"
    },
    {
        "Nome do Produto": "DANDELION - BRIGHTENING FACE POWDER",
        "Processo": "25351.658086/2011-23",
        "Nome da Empresa - CNPJ": "LVMH PARFUMS ET COSMETIQUES DO BRASIL LTDA - 02.193.054/0001-46",
        "Número do Registro": "226400768",
        "Situação": "ATIVO",
        "Vencimento": "23/01/2027",
        "link": "https://consultas.anvisa.gov.br/#/cosmeticos/registrados/25351658086201123/?dataInicial=2027-01-23&dataFinal=2027-01-23",
        "Nome da Empresa": "LVMH PARFUMS ET COSMETIQUES DO BRASIL LTDA",
        "Número do CNPJ da Empresa": "02.193.054/0001-46",
        "Categoria": "PÓ FACIAL COMPACTO SEM FINALIDADE FOTOPROTETORA DA PELE",
        "Publicação do Registro": "23/01/2012",
        "Vencimento do Registro": "23/01/2027",
        "Situação do Produto": "ATIVO"
    },
    {
        "Nome do Produto": "DERMOPLEX COLOR TONALIZANTE BEGE FPS 45",
        "Processo": "25351.302636/2016-17",
        "Nome da Empresa - CNPJ": "ANCLA´S INDÚSTRIA E COMÉRCIO DE COSMÉTICOS LTDA - EPP - 19.138.182/0001-90",
        "Número do Registro": "275470043",
        "Situação": "INATIVO",
        "Vencimento": "23/01/2027",
        "link": "https://consultas.anvisa.gov.br/#/cosmeticos/registrados/25351302636201617/?dataInicial=2027-01-23&dataFinal=2027-01-23",
        "Nome da Empresa": "ANCLA´S INDÚSTRIA E COMÉRCIO DE COSMÉTICOS LTDA - EPP",
        "Número do CNPJ da Empresa": "19.138.182/0001-90",
        "Categoria": "PROTETOR SOLAR - GRAU 2",
        "Publicação do Registro": "23/01/2017",
        "Vencimento do Registro": "23/01/2027",
        "Situação do Produto": "INATIVO"
    },
    {
        "Nome do Produto": "DIA A DIA PROTETOR SOLAR FPS 50",
        "Processo": "25351.310770/2016-13",
        "Nome da Empresa - CNPJ": "Francefarma Indústria de Cosméticos ltda - 18.575.413/0001-60",
        "Número do Registro": "278300025",
        "Situação": "INATIVO",
        "Vencimento": "23/01/2027",
        "link": "https://consultas.anvisa.gov.br/#/cosmeticos/registrados/25351310770201613/?dataInicial=2027-01-23&dataFinal=2027-01-23",
        "Nome da Empresa": "Francefarma Indústria de Cosméticos ltda",
        "Número do CNPJ da Empresa": "18.575.413/0001-60",
        "Categoria": "PROTETOR SOLAR - GRAU 2",
        "Publicação do Registro": "23/01/2017",
        "Vencimento do Registro": "23/01/2027",
        "Situação do Produto": "INATIVO"
    },
    {
        "Nome do Produto": "DOKINHA LOÇÃO HIDRATANTE - DOKMOS",
        "Processo": "25351.316834/2016-09",
        "Nome da Empresa - CNPJ": "W I INDÚSTRIA COMÉRCIO E DISTRIBUIÇÃO DE COSMÉTICOS LTDA - 11.878.065/0001-50",
        "Número do Registro": "262360012",
        "Situação": "INATIVO",
        "Vencimento": "23/01/2027",
        "link": "https://consultas.anvisa.gov.br/#/cosmeticos/registrados/25351316834201609/?dataInicial=2027-01-23&dataFinal=2027-01-23",
        "Nome da Empresa": "W I INDÚSTRIA COMÉRCIO  E DISTRIBUIÇÃO DE COSMÉTICOS LTDA",
        "Número do CNPJ da Empresa": "11.878.065/0001-50",
        "Categoria": "HIDRATANTE PARA PELE INFANTIL - GRAU 2",
        "Publicação do Registro": "23/01/2017",
        "Vencimento do Registro": "23/01/2027",
        "Situação do Produto": "INATIVO"
    },
    {
        "Nome do Produto": "GARNIER BI-O MINERAL EXTREME ICE",
        "Processo": "25351.703766/2011-88",
        "Nome da Empresa - CNPJ": "PROCOSA PRODUTOS DE BELEZA LTDA - 33.306.929/0001-00",
        "Número do Registro": "200703734",
        "Situação": "ATIVO",
        "Vencimento": "23/01/2027",
        "link": "https://consultas.anvisa.gov.br/#/cosmeticos/registrados/25351703766201188/?dataInicial=2027-01-23&dataFinal=2027-01-23",
        "Nome da Empresa": "PROCOSA PRODUTOS DE BELEZA LTDA",
        "Número do CNPJ da Empresa": "33.306.929/0001-00",
        "Categoria": "ANTITRANSPIRANTE/ANTIPERSPIRANTE AXILAR (PERFUMADO OU NÃO SOB A FORMA DE LÍQUIDO, GEL, CREME, SÓLIDO OU AEROSSOL)",
        "Publicação do Registro": "23/01/2012",
        "Vencimento do Registro": "23/01/2027",
        "Situação do Produto": "ATIVO"
    },
    {
        "Nome do Produto": "GEL DENTAL INFANTIL DOCTOR DUCK DENTALCLEAN",
        "Processo": "25351.351548/2016-29",
        "Nome da Empresa - CNPJ": "RABBIT INDÚSTRIA E COMÉRCIO DE PRODUTOS DE HIGIENE PESSOAL LTDA - 00.099.817/0001-69",
        "Número do Registro": "229740031",
        "Situação": "ATIVO",
        "Vencimento": "23/01/2027",
        "link": "https://consultas.anvisa.gov.br/#/cosmeticos/registrados/25351351548201629/?dataInicial=2027-01-23&dataFinal=2027-01-23",
        "Nome da Empresa": "RABBIT INDÚSTRIA E COMÉRCIO DE PRODUTOS DE HIGIENE PESSOAL LTDA",
        "Número do CNPJ da Empresa": "00.099.817/0001-69",
        "Categoria": "DENTIFRÍCIO COM OU SEM FLÚOR INFANTIL - GRAU 2",
        "Publicação do Registro": "23/01/2017",
        "Vencimento do Registro": "23/01/2027",
        "Situação do Produto": "ATIVO"
    },
    {
        "Nome do Produto": "HIDRACTIVE GEL PLUS HIDRATANTE E NUTRITIVO CLAREMOM",
        "Processo": "25351.715729/2011-82",
        "Nome da Empresa - CNPJ": "ALIANZA INDÚSTRIA E COMÉRCIO DE COSMÉETICOS LTDA EPP - 03.982.695/0001-42",
        "Número do Registro": "231020421",
        "Situação": "ATIVO",
        "Vencimento": "23/01/2027",
        "link": "https://consultas.anvisa.gov.br/#/cosmeticos/registrados/25351715729201182/?dataInicial=2027-01-23&dataFinal=2027-01-23",
        "Nome da Empresa": "ALIANZA INDÚSTRIA E COMÉRCIO DE COSMÉETICOS LTDA EPP",
        "Número do CNPJ da Empresa": "03.982.695/0001-42",
        "Categoria": "CREME PARA RUGAS (PERFUMADOS OU NÃO, INCLUINDO OS GÉIS)",
        "Publicação do Registro": "23/01/2012",
        "Vencimento do Registro": "23/01/2027",
        "Situação do Produto": "ATIVO"
    },
    {
        "Nome do Produto": "LENCOS UMEDECIDOS HIPOPÓ BABY",
        "Processo": "25351.316495/2016-04",
        "Nome da Empresa - CNPJ": "POWER SAVE INDUSTRIA E COMERCIO DE PRODUTOS PARA HIGIENE PESSOAL E TEXTIL LTDA - EPP - 68.146.992/0001-01",
        "Número do Registro": "268250009",
        "Situação": "INATIVO",
        "Vencimento": "23/01/2027",
        "link": "https://consultas.anvisa.gov.br/#/cosmeticos/registrados/25351316495201604/?dataInicial=2027-01-23&dataFinal=2027-01-23",
        "Nome da Empresa": "POWER SAVE INDUSTRIA E COMERCIO DE PRODUTOS PARA HIGIENE PESSOAL E TEXTIL LTDA - EPP",
        "Número do CNPJ da Empresa": "68.146.992/0001-01",
        "Categoria": "LENÇOS UMEDECIDOS PARA HIGIENE INFANTIL - GRAU 2",
        "Publicação do Registro": "23/01/2017",
        "Vencimento do Registro": "23/01/2027",
        "Situação do Produto": "INATIVO"
    },
    {
        "Nome do Produto": "LENÇOS UMEDECIDOS EVOLUTION BABY",
        "Processo": "25351.316426/2016-01",
        "Nome da Empresa - CNPJ": "POWER SAVE INDUSTRIA E COMERCIO DE PRODUTOS PARA HIGIENE PESSOAL E TEXTIL LTDA - EPP - 68.146.992/0001-01",
        "Número do Registro": "268250006",
        "Situação": "INATIVO",
        "Vencimento": "23/01/2027",
        "link": "https://consultas.anvisa.gov.br/#/cosmeticos/registrados/25351316426201601/?dataInicial=2027-01-23&dataFinal=2027-01-23",
        "Nome da Empresa": "POWER SAVE INDUSTRIA E COMERCIO DE PRODUTOS PARA HIGIENE PESSOAL E TEXTIL LTDA - EPP",
        "Número do CNPJ da Empresa": "68.146.992/0001-01",
        "Categoria": "LENÇOS UMEDECIDOS PARA HIGIENE INFANTIL - GRAU 2",
        "Publicação do Registro": "23/01/2017",
        "Vencimento do Registro": "23/01/2027",
        "Situação do Produto": "INATIVO"
    },
    {
        "Nome do Produto": "CREME RELAXANTE 3 - NORMAL- AFRONATURE",
        "Processo": "25351.044792/2016-36",
        "Nome da Empresa - CNPJ": "ATSUM INDÚSTRIA E COMÉRCIO DE COSMÉTICOS LTDA - 06.215.185/0001-38",
        "Número do Registro": "240880097",
        "Situação": "INATIVO",
        "Vencimento": "23/01/2027",
        "link": "https://consultas.anvisa.gov.br/#/cosmeticos/registrados/25351044792201636/?dataInicial=2027-01-23&dataFinal=2027-01-23",
        "Nome da Empresa": "ATSUM INDÚSTRIA E COMÉRCIO DE COSMÉTICOS LTDA",
        "Número do CNPJ da Empresa": "06.215.185/0001-38",
        "Categoria": "ALISANTE PARA CABELOS - GRAU 2",
        "Publicação do Registro": "23/01/2017",
        "Vencimento do Registro": "23/01/2027",
        "Situação do Produto": "INATIVO"
    },
    {
        "Nome do Produto": "DANDELION - BRIGHTENING FACE POWDER",
        "Processo": "25351.658086/2011-23",
        "Nome da Empresa - CNPJ": "LVMH PARFUMS ET COSMETIQUES DO BRASIL LTDA - 02.193.054/0001-46",
        "Número do Registro": "226400768",
        "Situação": "ATIVO",
        "Vencimento": "23/01/2027",
        "link": "https://consultas.anvisa.gov.br/#/cosmeticos/registrados/25351658086201123/?dataInicial=2027-01-23&dataFinal=2027-01-23",
        "Nome da Empresa": "LVMH PARFUMS ET COSMETIQUES DO BRASIL LTDA",
        "Número do CNPJ da Empresa": "02.193.054/0001-46",
        "Categoria": "PÓ FACIAL COMPACTO SEM FINALIDADE FOTOPROTETORA DA PELE",
        "Publicação do Registro": "23/01/2012",
        "Vencimento do Registro": "23/01/2027",
        "Situação do Produto": "ATIVO"
    },
    {
        "Nome do Produto": "DERMOPLEX COLOR TONALIZANTE BEGE FPS 45",
        "Processo": "25351.302636/2016-17",
        "Nome da Empresa - CNPJ": "ANCLA´S INDÚSTRIA E COMÉRCIO DE COSMÉTICOS LTDA - EPP - 19.138.182/0001-90",
        "Número do Registro": "275470043",
        "Situação": "INATIVO",
        "Vencimento": "23/01/2027",
        "link": "https://consultas.anvisa.gov.br/#/cosmeticos/registrados/25351302636201617/?dataInicial=2027-01-23&dataFinal=2027-01-23",
        "Nome da Empresa": "ANCLA´S INDÚSTRIA E COMÉRCIO DE COSMÉTICOS LTDA - EPP",
        "Número do CNPJ da Empresa": "19.138.182/0001-90",
        "Categoria": "PROTETOR SOLAR - GRAU 2",
        "Publicação do Registro": "23/01/2017",
        "Vencimento do Registro": "23/01/2027",
        "Situação do Produto": "INATIVO"
    },
    {
        "Nome do Produto": "DIA A DIA PROTETOR SOLAR FPS 50",
        "Processo": "25351.310770/2016-13",
        "Nome da Empresa - CNPJ": "Francefarma Indústria de Cosméticos ltda - 18.575.413/0001-60",
        "Número do Registro": "278300025",
        "Situação": "INATIVO",
        "Vencimento": "23/01/2027",
        "link": "https://consultas.anvisa.gov.br/#/cosmeticos/registrados/25351310770201613/?dataInicial=2027-01-23&dataFinal=2027-01-23",
        "Nome da Empresa": "Francefarma Indústria de Cosméticos ltda",
        "Número do CNPJ da Empresa": "18.575.413/0001-60",
        "Categoria": "PROTETOR SOLAR - GRAU 2",
        "Publicação do Registro": "23/01/2017",
        "Vencimento do Registro": "23/01/2027",
        "Situação do Produto": "INATIVO"
    },
    {
        "Nome do Produto": "DOKINHA LOÇÃO HIDRATANTE - DOKMOS",
        "Processo": "25351.316834/2016-09",
        "Nome da Empresa - CNPJ": "W I INDÚSTRIA COMÉRCIO E DISTRIBUIÇÃO DE COSMÉTICOS LTDA - 11.878.065/0001-50",
        "Número do Registro": "262360012",
        "Situação": "INATIVO",
        "Vencimento": "23/01/2027",
        "link": "https://consultas.anvisa.gov.br/#/cosmeticos/registrados/25351316834201609/?dataInicial=2027-01-23&dataFinal=2027-01-23",
        "Nome da Empresa": "W I INDÚSTRIA COMÉRCIO  E DISTRIBUIÇÃO DE COSMÉTICOS LTDA",
        "Número do CNPJ da Empresa": "11.878.065/0001-50",
        "Categoria": "HIDRATANTE PARA PELE INFANTIL - GRAU 2",
        "Publicação do Registro": "23/01/2017",
        "Vencimento do Registro": "23/01/2027",
        "Situação do Produto": "INATIVO"
    },
    {
        "Nome do Produto": "GARNIER BI-O MINERAL EXTREME ICE",
        "Processo": "25351.703766/2011-88",
        "Nome da Empresa - CNPJ": "PROCOSA PRODUTOS DE BELEZA LTDA - 33.306.929/0001-00",
        "Número do Registro": "200703734",
        "Situação": "ATIVO",
        "Vencimento": "23/01/2027",
        "link": "https://consultas.anvisa.gov.br/#/cosmeticos/registrados/25351703766201188/?dataInicial=2027-01-23&dataFinal=2027-01-23",
        "Nome da Empresa": "PROCOSA PRODUTOS DE BELEZA LTDA",
        "Número do CNPJ da Empresa": "33.306.929/0001-00",
        "Categoria": "ANTITRANSPIRANTE/ANTIPERSPIRANTE AXILAR (PERFUMADO OU NÃO SOB A FORMA DE LÍQUIDO, GEL, CREME, SÓLIDO OU AEROSSOL)",
        "Publicação do Registro": "23/01/2012",
        "Vencimento do Registro": "23/01/2027",
        "Situação do Produto": "ATIVO"
    },
    {
        "Nome do Produto": "GEL DENTAL INFANTIL DOCTOR DUCK DENTALCLEAN",
        "Processo": "25351.351548/2016-29",
        "Nome da Empresa - CNPJ": "RABBIT INDÚSTRIA E COMÉRCIO DE PRODUTOS DE HIGIENE PESSOAL LTDA - 00.099.817/0001-69",
        "Número do Registro": "229740031",
        "Situação": "ATIVO",
        "Vencimento": "23/01/2027",
        "link": "https://consultas.anvisa.gov.br/#/cosmeticos/registrados/25351351548201629/?dataInicial=2027-01-23&dataFinal=2027-01-23",
        "Nome da Empresa": "RABBIT INDÚSTRIA E COMÉRCIO DE PRODUTOS DE HIGIENE PESSOAL LTDA",
        "Número do CNPJ da Empresa": "00.099.817/0001-69",
        "Categoria": "DENTIFRÍCIO COM OU SEM FLÚOR INFANTIL - GRAU 2",
        "Publicação do Registro": "23/01/2017",
        "Vencimento do Registro": "23/01/2027",
        "Situação do Produto": "ATIVO"
    },
    {
        "Nome do Produto": "HIDRACTIVE GEL PLUS HIDRATANTE E NUTRITIVO CLAREMOM",
        "Processo": "25351.715729/2011-82",
        "Nome da Empresa - CNPJ": "ALIANZA INDÚSTRIA E COMÉRCIO DE COSMÉETICOS LTDA EPP - 03.982.695/0001-42",
        "Número do Registro": "231020421",
        "Situação": "ATIVO",
        "Vencimento": "23/01/2027",
        "link": "https://consultas.anvisa.gov.br/#/cosmeticos/registrados/25351715729201182/?dataInicial=2027-01-23&dataFinal=2027-01-23",
        "Nome da Empresa": "ALIANZA INDÚSTRIA E COMÉRCIO DE COSMÉETICOS LTDA EPP",
        "Número do CNPJ da Empresa": "03.982.695/0001-42",
        "Categoria": "CREME PARA RUGAS (PERFUMADOS OU NÃO, INCLUINDO OS GÉIS)",
        "Publicação do Registro": "23/01/2012",
        "Vencimento do Registro": "23/01/2027",
        "Situação do Produto": "ATIVO"
    },
    {
        "Nome do Produto": "LENCOS UMEDECIDOS HIPOPÓ BABY",
        "Processo": "25351.316495/2016-04",
        "Nome da Empresa - CNPJ": "POWER SAVE INDUSTRIA E COMERCIO DE PRODUTOS PARA HIGIENE PESSOAL E TEXTIL LTDA - EPP - 68.146.992/0001-01",
        "Número do Registro": "268250009",
        "Situação": "INATIVO",
        "Vencimento": "23/01/2027",
        "link": "https://consultas.anvisa.gov.br/#/cosmeticos/registrados/25351316495201604/?dataInicial=2027-01-23&dataFinal=2027-01-23",
        "Nome da Empresa": "POWER SAVE INDUSTRIA E COMERCIO DE PRODUTOS PARA HIGIENE PESSOAL E TEXTIL LTDA - EPP",
        "Número do CNPJ da Empresa": "68.146.992/0001-01",
        "Categoria": "LENÇOS UMEDECIDOS PARA HIGIENE INFANTIL - GRAU 2",
        "Publicação do Registro": "23/01/2017",
        "Vencimento do Registro": "23/01/2027",
        "Situação do Produto": "INATIVO"
    },
    {
        "Nome do Produto": "LENÇOS UMEDECIDOS EVOLUTION BABY",
        "Processo": "25351.316426/2016-01",
        "Nome da Empresa - CNPJ": "POWER SAVE INDUSTRIA E COMERCIO DE PRODUTOS PARA HIGIENE PESSOAL E TEXTIL LTDA - EPP - 68.146.992/0001-01",
        "Número do Registro": "268250006",
        "Situação": "INATIVO",
        "Vencimento": "23/01/2027",
        "link": "https://consultas.anvisa.gov.br/#/cosmeticos/registrados/25351316426201601/?dataInicial=2027-01-23&dataFinal=2027-01-23",
        "Nome da Empresa": "POWER SAVE INDUSTRIA E COMERCIO DE PRODUTOS PARA HIGIENE PESSOAL E TEXTIL LTDA - EPP",
        "Número do CNPJ da Empresa": "68.146.992/0001-01",
        "Categoria": "LENÇOS UMEDECIDOS PARA HIGIENE INFANTIL - GRAU 2",
        "Publicação do Registro": "23/01/2017",
        "Vencimento do Registro": "23/01/2027",
        "Situação do Produto": "INATIVO"
    },
    {
        "Nome do Produto": "LOÇÃO REPELENTE MOSKITOFF BABY FARMAX",
        "Processo": "25351.442184/2016-01",
        "Nome da Empresa - CNPJ": "FARMAX S.A. - 21.759.758/0001-88",
        "Número do Registro": "231220132",
        "Situação": "ATIVO",
        "Vencimento": "23/01/2027",
        "link": "https://consultas.anvisa.gov.br/#/cosmeticos/registrados/25351442184201601/?dataInicial=2027-01-23&dataFinal=2027-01-23",
        "Nome da Empresa": "FARMAX S.A.",
        "Número do CNPJ da Empresa": "21.759.758/0001-88",
        "Categoria": "REPELENTE DE INSETOS INFANTIL - GRAU 2",
        "Publicação do Registro": "23/01/2017",
        "Vencimento do Registro": "23/01/2027",
        "Situação do Produto": "ATIVO"
    },
    {
        "Nome do Produto": "MAIS ÍNTIMA - DESODORANTE ÍNTIMO FEMININO AROMA VANILLA - ESSENCIAL BY HIROSHIMA",
        "Processo": "25351.708152/2011-05",
        "Nome da Empresa - CNPJ": "KENZO DO BRASIL INDÚSTRIA E COMÉRCIO LTDA - 52.496.916/0001-88",
        "Número do Registro": "207220206",
        "Situação": "ATIVO",
        "Vencimento": "23/01/2027",
        "link": "https://consultas.anvisa.gov.br/#/cosmeticos/registrados/25351708152201105/?dataInicial=2027-01-23&dataFinal=2027-01-23",
        "Nome da Empresa": "KENZO DO BRASIL INDÚSTRIA E COMÉRCIO LTDA",
        "Número do CNPJ da Empresa": "52.496.916/0001-88",
        "Categoria": "DESODORANTE ÍNTIMO (PERFUMADO OU NÃO, SOB A FORMA DE LÍQUIDO, GEL, CREME, SÓLIDO OU AEROSSOL)",
        "Publicação do Registro": "23/01/2012",
        "Vencimento do Registro": "23/01/2027",
        "Situação do Produto": "ATIVO"
    },
    {
        "Nome do Produto": "MANUTENÇÃO INTENSIVA NATU HAIR SOS KIDS MENINOS",
        "Processo": "25351.345827/2016-05",
        "Nome da Empresa - CNPJ": "BIOSENSE INDUSTRIA E COMERCIO DE PRODUTOS DE COSMETICA LTDA - 30.066.989/0001-05",
        "Número do Registro": "213850330",
        "Situação": "ATIVO",
        "Vencimento": "23/01/2027",
        "link": "https://consultas.anvisa.gov.br/#/cosmeticos/registrados/25351345827201605/?dataInicial=2027-01-23&dataFinal=2027-01-23",
        "Nome da Empresa": "BIOSENSE INDUSTRIA E COMERCIO DE PRODUTOS DE COSMETICA LTDA",
        "Número do CNPJ da Empresa": "30.066.989/0001-05",
        "Categoria": "CONDICIONADOR INFANTIL SEM ENXÁGUE - GRAU 2",
        "Publicação do Registro": "23/01/2017",
        "Vencimento do Registro": "23/01/2027",
        "Situação do Produto": "ATIVO"
    },
    {
        "Nome do Produto": "MEU SOL FPS 30",
        "Processo": "25351.238165/2016-74",
        "Nome da Empresa - CNPJ": "HADASSAH COSMÉTICOS LTDA - 07.967.729/0001-80",
        "Número do Registro": "243630026",
        "Situação": "ATIVO",
        "Vencimento": "23/01/2027",
        "link": "https://consultas.anvisa.gov.br/#/cosmeticos/registrados/25351238165201674/?dataInicial=2027-01-23&dataFinal=2027-01-23",
        "Nome da Empresa": "HADASSAH COSMÉTICOS LTDA",
        "Número do CNPJ da Empresa": "07.967.729/0001-80",
        "Categoria": "PROTETOR SOLAR - GRAU 2",
        "Publicação do Registro": "23/01/2017",
        "Vencimento do Registro": "23/01/2027",
        "Situação do Produto": "ATIVO"
    },
    {
        "Nome do Produto": "MEU SOL FPS 50 TROL",
        "Processo": "25351.358623/2016-65",
        "Nome da Empresa - CNPJ": "HADASSAH COSMÉTICOS LTDA - 07.967.729/0001-80",
        "Número do Registro": "243630025",
        "Situação": "ATIVO",
        "Vencimento": "23/01/2027",
        "link": "https://consultas.anvisa.gov.br/#/cosmeticos/registrados/25351358623201665/?dataInicial=2027-01-23&dataFinal=2027-01-23",
        "Nome da Empresa": "HADASSAH COSMÉTICOS LTDA",
        "Número do CNPJ da Empresa": "07.967.729/0001-80",
        "Categoria": "PROTETOR SOLAR - GRAU 2",
        "Publicação do Registro": "23/01/2017",
        "Vencimento do Registro": "23/01/2027",
        "Situação do Produto": "ATIVO"
    },
    {
        "Nome do Produto": "MUSTELA GEL LAVANTE SUAVE",
        "Processo": "25351.313695/2016-80",
        "Nome da Empresa - CNPJ": "LABORATÓRIOS EXPANSCIENCE COMÉRCIO IMPORTAÇÃO E EXPORTAÇÃO DE PRODUTOS PARA A SAÚDE LTDA - 08.160.941/0001-02",
        "Número do Registro": "262190037",
        "Situação": "ATIVO",
        "Vencimento": "23/01/2027",
        "link": "https://consultas.anvisa.gov.br/#/cosmeticos/registrados/25351313695201680/?dataInicial=2027-01-23&dataFinal=2027-01-23",
        "Nome da Empresa": "LABORATÓRIOS EXPANSCIENCE COMÉRCIO IMPORTAÇÃO E EXPORTAÇÃO DE PRODUTOS PARA A SAÚDE LTDA",
        "Número do CNPJ da Empresa": "08.160.941/0001-02",
        "Categoria": "SABONETE INFANTIL - GRAU 2",
        "Publicação do Registro": "23/01/2017",
        "Vencimento do Registro": "23/01/2027",
        "Situação do Produto": "ATIVO"
    },
    {
        "Nome do Produto": "MUSTELA HYDRA BEBE LEITE CORPORAL",
        "Processo": "25351.313759/2016-23",
        "Nome da Empresa - CNPJ": "LABORATÓRIOS EXPANSCIENCE COMÉRCIO IMPORTAÇÃO E EXPORTAÇÃO DE PRODUTOS PARA A SAÚDE LTDA - 08.160.941/0001-02",
        "Número do Registro": "262190038",
        "Situação": "ATIVO",
        "Vencimento": "23/01/2027",
        "link": "https://consultas.anvisa.gov.br/#/cosmeticos/registrados/25351313759201623/?dataInicial=2027-01-23&dataFinal=2027-01-23",
        "Nome da Empresa": "LABORATÓRIOS EXPANSCIENCE COMÉRCIO IMPORTAÇÃO E EXPORTAÇÃO DE PRODUTOS PARA A SAÚDE LTDA",
        "Número do CNPJ da Empresa": "08.160.941/0001-02",
        "Categoria": "HIDRATANTE PARA PELE INFANTIL - GRAU 2",
        "Publicação do Registro": "23/01/2017",
        "Vencimento do Registro": "23/01/2027",
        "Situação do Produto": "ATIVO"
    },
    {
        "Nome do Produto": "OXIDANT RICHE EFFECT ONE 20 VOLUMES LUMINOSITÉ",
        "Processo": "25351.716421/2011-33",
        "Nome da Empresa - CNPJ": "T.C.I INDÚSTRIA COSMÉTICA LTDA-EPP - 07.239.476/0001-29",
        "Número do Registro": "240760101",
        "Situação": "ATIVO",
        "Vencimento": "23/01/2027",
        "link": "https://consultas.anvisa.gov.br/#/cosmeticos/registrados/25351716421201133/?dataInicial=2027-01-23&dataFinal=2027-01-23",
        "Nome da Empresa": "T.C.I INDÚSTRIA COSMÉTICA LTDA-EPP",
        "Número do CNPJ da Empresa": "07.239.476/0001-29",
        "Categoria": "ÁGUA OXIGENADA (10 A 40 VOLUMES) (INCLUÍDAS AS CREMOSAS, EXCETO OS PRODUTOS DE USO MEDICINAL)",
        "Publicação do Registro": "23/01/2012",
        "Vencimento do Registro": "23/01/2027",
        "Situação do Produto": "ATIVO"
    },
    {
        "Nome do Produto": "OXIDANT RICHE EFFECT TWO 40 VOLUMES LUMINISITÉ",
        "Processo": "25351.716402/2011-18",
        "Nome da Empresa - CNPJ": "T.C.I INDÚSTRIA COSMÉTICA LTDA-EPP - 07.239.476/0001-29",
        "Número do Registro": "240760100",
        "Situação": "ATIVO",
        "Vencimento": "23/01/2027",
        "link": "https://consultas.anvisa.gov.br/#/cosmeticos/registrados/25351716402201118/?dataInicial=2027-01-23&dataFinal=2027-01-23",
        "Nome da Empresa": "T.C.I INDÚSTRIA COSMÉTICA LTDA-EPP",
        "Número do CNPJ da Empresa": "07.239.476/0001-29",
        "Categoria": "ÁGUA OXIGENADA (10 A 40 VOLUMES) (INCLUÍDAS AS CREMOSAS, EXCETO OS PRODUTOS DE USO MEDICINAL)",
        "Publicação do Registro": "23/01/2012",
        "Vencimento do Registro": "23/01/2027",
        "Situação do Produto": "ATIVO"
    },
    {
        "Nome do Produto": "PROFIT NEMAWASHI VELVET LOÇÃO PROTETORA SOLAR FPS 30",
        "Processo": "25351.313739/2016-90",
        "Nome da Empresa - CNPJ": "NASI INDUSTRIA DE NUTRICOSMÉTICOS LTDA - ME - 08.908.883/0001-44",
        "Número do Registro": "252530020",
        "Situação": "INATIVO",
        "Vencimento": "23/01/2027",
        "link": "https://consultas.anvisa.gov.br/#/cosmeticos/registrados/25351313739201690/?dataInicial=2027-01-23&dataFinal=2027-01-23",
        "Nome da Empresa": "NASI INDUSTRIA DE NUTRICOSMÉTICOS LTDA - ME",
        "Número do CNPJ da Empresa": "08.908.883/0001-44",
        "Categoria": "PROTETOR SOLAR - GRAU 2",
        "Publicação do Registro": "23/01/2017",
        "Vencimento do Registro": "23/01/2027",
        "Situação do Produto": "INATIVO"
    },
    {
        "Nome do Produto": "LOÇÃO REPELENTE MOSKITOFF BABY FARMAX",
        "Processo": "25351.442184/2016-01",
        "Nome da Empresa - CNPJ": "FARMAX S.A. - 21.759.758/0001-88",
        "Número do Registro": "231220132",
        "Situação": "ATIVO",
        "Vencimento": "23/01/2027",
        "link": "https://consultas.anvisa.gov.br/#/cosmeticos/registrados/25351442184201601/?dataInicial=2027-01-23&dataFinal=2027-01-23",
        "Nome da Empresa": "FARMAX S.A.",
        "Número do CNPJ da Empresa": "21.759.758/0001-88",
        "Categoria": "REPELENTE DE INSETOS INFANTIL - GRAU 2",
        "Publicação do Registro": "23/01/2017",
        "Vencimento do Registro": "23/01/2027",
        "Situação do Produto": "ATIVO"
    },
    {
        "Nome do Produto": "MAIS ÍNTIMA - DESODORANTE ÍNTIMO FEMININO AROMA VANILLA - ESSENCIAL BY HIROSHIMA",
        "Processo": "25351.708152/2011-05",
        "Nome da Empresa - CNPJ": "KENZO DO BRASIL INDÚSTRIA E COMÉRCIO LTDA - 52.496.916/0001-88",
        "Número do Registro": "207220206",
        "Situação": "ATIVO",
        "Vencimento": "23/01/2027",
        "link": "https://consultas.anvisa.gov.br/#/cosmeticos/registrados/25351708152201105/?dataInicial=2027-01-23&dataFinal=2027-01-23",
        "Nome da Empresa": "KENZO DO BRASIL INDÚSTRIA E COMÉRCIO LTDA",
        "Número do CNPJ da Empresa": "52.496.916/0001-88",
        "Categoria": "DESODORANTE ÍNTIMO (PERFUMADO OU NÃO, SOB A FORMA DE LÍQUIDO, GEL, CREME, SÓLIDO OU AEROSSOL)",
        "Publicação do Registro": "23/01/2012",
        "Vencimento do Registro": "23/01/2027",
        "Situação do Produto": "ATIVO"
    },
    {
        "Nome do Produto": "MANUTENÇÃO INTENSIVA NATU HAIR SOS KIDS MENINOS",
        "Processo": "25351.345827/2016-05",
        "Nome da Empresa - CNPJ": "BIOSENSE INDUSTRIA E COMERCIO DE PRODUTOS DE COSMETICA LTDA - 30.066.989/0001-05",
        "Número do Registro": "213850330",
        "Situação": "ATIVO",
        "Vencimento": "23/01/2027",
        "link": "https://consultas.anvisa.gov.br/#/cosmeticos/registrados/25351345827201605/?dataInicial=2027-01-23&dataFinal=2027-01-23",
        "Nome da Empresa": "BIOSENSE INDUSTRIA E COMERCIO DE PRODUTOS DE COSMETICA LTDA",
        "Número do CNPJ da Empresa": "30.066.989/0001-05",
        "Categoria": "CONDICIONADOR INFANTIL SEM ENXÁGUE - GRAU 2",
        "Publicação do Registro": "23/01/2017",
        "Vencimento do Registro": "23/01/2027",
        "Situação do Produto": "ATIVO"
    },
    {
        "Nome do Produto": "MEU SOL FPS 30",
        "Processo": "25351.238165/2016-74",
        "Nome da Empresa - CNPJ": "HADASSAH COSMÉTICOS LTDA - 07.967.729/0001-80",
        "Número do Registro": "243630026",
        "Situação": "ATIVO",
        "Vencimento": "23/01/2027",
        "link": "https://consultas.anvisa.gov.br/#/cosmeticos/registrados/25351238165201674/?dataInicial=2027-01-23&dataFinal=2027-01-23",
        "Nome da Empresa": "HADASSAH COSMÉTICOS LTDA",
        "Número do CNPJ da Empresa": "07.967.729/0001-80",
        "Categoria": "PROTETOR SOLAR - GRAU 2",
        "Publicação do Registro": "23/01/2017",
        "Vencimento do Registro": "23/01/2027",
        "Situação do Produto": "ATIVO"
    },
    {
        "Nome do Produto": "MEU SOL FPS 50 TROL",
        "Processo": "25351.358623/2016-65",
        "Nome da Empresa - CNPJ": "HADASSAH COSMÉTICOS LTDA - 07.967.729/0001-80",
        "Número do Registro": "243630025",
        "Situação": "ATIVO",
        "Vencimento": "23/01/2027",
        "link": "https://consultas.anvisa.gov.br/#/cosmeticos/registrados/25351358623201665/?dataInicial=2027-01-23&dataFinal=2027-01-23",
        "Nome da Empresa": "HADASSAH COSMÉTICOS LTDA",
        "Número do CNPJ da Empresa": "07.967.729/0001-80",
        "Categoria": "PROTETOR SOLAR - GRAU 2",
        "Publicação do Registro": "23/01/2017",
        "Vencimento do Registro": "23/01/2027",
        "Situação do Produto": "ATIVO"
    },
    {
        "Nome do Produto": "MUSTELA GEL LAVANTE SUAVE",
        "Processo": "25351.313695/2016-80",
        "Nome da Empresa - CNPJ": "LABORATÓRIOS EXPANSCIENCE COMÉRCIO IMPORTAÇÃO E EXPORTAÇÃO DE PRODUTOS PARA A SAÚDE LTDA - 08.160.941/0001-02",
        "Número do Registro": "262190037",
        "Situação": "ATIVO",
        "Vencimento": "23/01/2027",
        "link": "https://consultas.anvisa.gov.br/#/cosmeticos/registrados/25351313695201680/?dataInicial=2027-01-23&dataFinal=2027-01-23",
        "Nome da Empresa": "LABORATÓRIOS EXPANSCIENCE COMÉRCIO IMPORTAÇÃO E EXPORTAÇÃO DE PRODUTOS PARA A SAÚDE LTDA",
        "Número do CNPJ da Empresa": "08.160.941/0001-02",
        "Categoria": "SABONETE INFANTIL - GRAU 2",
        "Publicação do Registro": "23/01/2017",
        "Vencimento do Registro": "23/01/2027",
        "Situação do Produto": "ATIVO"
    },
    {
        "Nome do Produto": "MUSTELA HYDRA BEBE LEITE CORPORAL",
        "Processo": "25351.313759/2016-23",
        "Nome da Empresa - CNPJ": "LABORATÓRIOS EXPANSCIENCE COMÉRCIO IMPORTAÇÃO E EXPORTAÇÃO DE PRODUTOS PARA A SAÚDE LTDA - 08.160.941/0001-02",
        "Número do Registro": "262190038",
        "Situação": "ATIVO",
        "Vencimento": "23/01/2027",
        "link": "https://consultas.anvisa.gov.br/#/cosmeticos/registrados/25351313759201623/?dataInicial=2027-01-23&dataFinal=2027-01-23",
        "Nome da Empresa": "LABORATÓRIOS EXPANSCIENCE COMÉRCIO IMPORTAÇÃO E EXPORTAÇÃO DE PRODUTOS PARA A SAÚDE LTDA",
        "Número do CNPJ da Empresa": "08.160.941/0001-02",
        "Categoria": "HIDRATANTE PARA PELE INFANTIL - GRAU 2",
        "Publicação do Registro": "23/01/2017",
        "Vencimento do Registro": "23/01/2027",
        "Situação do Produto": "ATIVO"
    },
    {
        "Nome do Produto": "OXIDANT RICHE EFFECT ONE 20 VOLUMES LUMINOSITÉ",
        "Processo": "25351.716421/2011-33",
        "Nome da Empresa - CNPJ": "T.C.I INDÚSTRIA COSMÉTICA LTDA-EPP - 07.239.476/0001-29",
        "Número do Registro": "240760101",
        "Situação": "ATIVO",
        "Vencimento": "23/01/2027",
        "link": "https://consultas.anvisa.gov.br/#/cosmeticos/registrados/25351716421201133/?dataInicial=2027-01-23&dataFinal=2027-01-23",
        "Nome da Empresa": "T.C.I INDÚSTRIA COSMÉTICA LTDA-EPP",
        "Número do CNPJ da Empresa": "07.239.476/0001-29",
        "Categoria": "ÁGUA OXIGENADA (10 A 40 VOLUMES) (INCLUÍDAS AS CREMOSAS, EXCETO OS PRODUTOS DE USO MEDICINAL)",
        "Publicação do Registro": "23/01/2012",
        "Vencimento do Registro": "23/01/2027",
        "Situação do Produto": "ATIVO"
    },
    {
        "Nome do Produto": "OXIDANT RICHE EFFECT TWO 40 VOLUMES LUMINISITÉ",
        "Processo": "25351.716402/2011-18",
        "Nome da Empresa - CNPJ": "T.C.I INDÚSTRIA COSMÉTICA LTDA-EPP - 07.239.476/0001-29",
        "Número do Registro": "240760100",
        "Situação": "ATIVO",
        "Vencimento": "23/01/2027",
        "link": "https://consultas.anvisa.gov.br/#/cosmeticos/registrados/25351716402201118/?dataInicial=2027-01-23&dataFinal=2027-01-23",
        "Nome da Empresa": "T.C.I INDÚSTRIA COSMÉTICA LTDA-EPP",
        "Número do CNPJ da Empresa": "07.239.476/0001-29",
        "Categoria": "ÁGUA OXIGENADA (10 A 40 VOLUMES) (INCLUÍDAS AS CREMOSAS, EXCETO OS PRODUTOS DE USO MEDICINAL)",
        "Publicação do Registro": "23/01/2012",
        "Vencimento do Registro": "23/01/2027",
        "Situação do Produto": "ATIVO"
    },
    {
        "Nome do Produto": "PROFIT NEMAWASHI VELVET LOÇÃO PROTETORA SOLAR FPS 30",
        "Processo": "25351.313739/2016-90",
        "Nome da Empresa - CNPJ": "NASI INDUSTRIA DE NUTRICOSMÉTICOS LTDA - ME - 08.908.883/0001-44",
        "Número do Registro": "252530020",
        "Situação": "INATIVO",
        "Vencimento": "23/01/2027",
        "link": "https://consultas.anvisa.gov.br/#/cosmeticos/registrados/25351313739201690/?dataInicial=2027-01-23&dataFinal=2027-01-23",
        "Nome da Empresa": "NASI INDUSTRIA DE NUTRICOSMÉTICOS LTDA - ME",
        "Número do CNPJ da Empresa": "08.908.883/0001-44",
        "Categoria": "PROTETOR SOLAR - GRAU 2",
        "Publicação do Registro": "23/01/2017",
        "Vencimento do Registro": "23/01/2027",
        "Situação do Produto": "INATIVO"
    },
    {
        "Nome do Produto": "PROTETOR SOLAR ALERGOSUN FPS 60 ALERGOSHOP",
        "Processo": "25351.302623/2016-18",
        "Nome da Empresa - CNPJ": "ANCLA´S INDÚSTRIA E COMÉRCIO DE COSMÉTICOS LTDA - EPP - 19.138.182/0001-90",
        "Número do Registro": "275470042",
        "Situação": "INATIVO",
        "Vencimento": "23/01/2027",
        "link": "https://consultas.anvisa.gov.br/#/cosmeticos/registrados/25351302623201618/?dataInicial=2027-01-23&dataFinal=2027-01-23",
        "Nome da Empresa": "ANCLA´S INDÚSTRIA E COMÉRCIO DE COSMÉTICOS LTDA - EPP",
        "Número do CNPJ da Empresa": "19.138.182/0001-90",
        "Categoria": "PROTETOR SOLAR - GRAU 2",
        "Publicação do Registro": "23/01/2017",
        "Vencimento do Registro": "23/01/2027",
        "Situação do Produto": "INATIVO"
    },
    {
        "Nome do Produto": "PROTETOR SOLAR INFANTIL FPS 50 NINI E JUI - UB COSMÉTICOS",
        "Processo": "25351.326040/2016-90",
        "Nome da Empresa - CNPJ": "L`AROMATIC INDUSTRIA E COMERCIO LTDA - 17.470.182/0001-67",
        "Número do Registro": "270090007",
        "Situação": "INATIVO",
        "Vencimento": "23/01/2027",
        "link": "https://consultas.anvisa.gov.br/#/cosmeticos/registrados/25351326040201690/?dataInicial=2027-01-23&dataFinal=2027-01-23",
        "Nome da Empresa": "L`AROMATIC INDUSTRIA E COMERCIO LTDA",
        "Número do CNPJ da Empresa": "17.470.182/0001-67",
        "Categoria": "PROTETOR SOLAR INFANTIL - GRAU 2",
        "Publicação do Registro": "23/01/2017",
        "Vencimento do Registro": "23/01/2027",
        "Situação do Produto": "INATIVO"
    },
    {
        "Nome do Produto": "QUEM DISSE, BERENICE? BATOM GLITTER",
        "Processo": "25351.717076/2011-27",
        "Nome da Empresa - CNPJ": "BOTICA COMERCIAL FARMACEUTICA LTDA. - 77.388.007/0001-57",
        "Número do Registro": "205441257",
        "Situação": "ATIVO",
        "Vencimento": "23/01/2027",
        "link": "https://consultas.anvisa.gov.br/#/cosmeticos/registrados/25351717076201127/?dataInicial=2027-01-23&dataFinal=2027-01-23",
        "Nome da Empresa": "BOTICA COMERCIAL FARMACEUTICA LTDA.",
        "Número do CNPJ da Empresa": "77.388.007/0001-57",
        "Categoria": "BATOM COM FINALIDADE FOTOPROTETORA (LÍQUIDO, CREME OU SÓLIDO)",
        "Publicação do Registro": "23/01/2012",
        "Vencimento do Registro": "23/01/2027",
        "Situação do Produto": "ATIVO"
    },
    {
        "Nome do Produto": "QUEM DISSE, BERENICE? BATOM MATE",
        "Processo": "25351.716693/2011-33",
        "Nome da Empresa - CNPJ": "BOTICA COMERCIAL FARMACEUTICA LTDA. - 77.388.007/0001-57",
        "Número do Registro": "205441258",
        "Situação": "ATIVO",
        "Vencimento": "23/01/2027",
        "link": "https://consultas.anvisa.gov.br/#/cosmeticos/registrados/25351716693201133/?dataInicial=2027-01-23&dataFinal=2027-01-23",
        "Nome da Empresa": "BOTICA COMERCIAL FARMACEUTICA LTDA.",
        "Número do CNPJ da Empresa": "77.388.007/0001-57",
        "Categoria": "BATOM COM FINALIDADE FOTOPROTETORA (LÍQUIDO, CREME OU SÓLIDO)",
        "Publicação do Registro": "23/01/2012",
        "Vencimento do Registro": "23/01/2027",
        "Situação do Produto": "ATIVO"
    },
    {
        "Nome do Produto": "REDERMIC R",
        "Processo": "25351.703715/2011-60",
        "Nome da Empresa - CNPJ": "PROCOSA PRODUTOS DE BELEZA LTDA - 33.306.929/0001-00",
        "Número do Registro": "200703733",
        "Situação": "ATIVO",
        "Vencimento": "23/01/2027",
        "link": "https://consultas.anvisa.gov.br/#/cosmeticos/registrados/25351703715201160/?dataInicial=2027-01-23&dataFinal=2027-01-23",
        "Nome da Empresa": "PROCOSA PRODUTOS DE BELEZA LTDA",
        "Número do CNPJ da Empresa": "33.306.929/0001-00",
        "Categoria": "CREME OU LOÇÃO PARA O ROSTO COM FOTOPROTETOR DA PELE E/ou COM OUTRAS FINALIDADES ALÉM DA HIDRATAÇÃO (PERFUMADOS OU NÃO, INCLUINDO OS GÉIS)",
        "Publicação do Registro": "23/01/2012",
        "Vencimento do Registro": "23/01/2027",
        "Situação do Produto": "ATIVO"
    },
    {
        "Nome do Produto": "SHAMPOO FLORESTA EXTRATO DE GUARANÁ RED O MICO - UB COSMÉTICOS",
        "Processo": "25351.326035/2016-10",
        "Nome da Empresa - CNPJ": "L`AROMATIC INDUSTRIA E COMERCIO LTDA - 17.470.182/0001-67",
        "Número do Registro": "270090006",
        "Situação": "INATIVO",
        "Vencimento": "23/01/2027",
        "link": "https://consultas.anvisa.gov.br/#/cosmeticos/registrados/25351326035201610/?dataInicial=2027-01-23&dataFinal=2027-01-23",
        "Nome da Empresa": "L`AROMATIC INDUSTRIA E COMERCIO LTDA",
        "Número do CNPJ da Empresa": "17.470.182/0001-67",
        "Categoria": "XAMPU/XAMPU CONDICIONADOR INFANTIL - GRAU 2",
        "Publicação do Registro": "23/01/2017",
        "Vencimento do Registro": "23/01/2027",
        "Situação do Produto": "INATIVO"
    },
    {
        "Nome do Produto": "SKIN BODY PROTETOR SOLAR FPS 30",
        "Processo": "25351.310769/2016-43",
        "Nome da Empresa - CNPJ": "Francefarma Indústria de Cosméticos ltda - 18.575.413/0001-60",
        "Número do Registro": "278300026",
        "Situação": "INATIVO",
        "Vencimento": "23/01/2027",
        "link": "https://consultas.anvisa.gov.br/#/cosmeticos/registrados/25351310769201643/?dataInicial=2027-01-23&dataFinal=2027-01-23",
        "Nome da Empresa": "Francefarma Indústria de Cosméticos ltda",
        "Número do CNPJ da Empresa": "18.575.413/0001-60",
        "Categoria": "PROTETOR SOLAR - GRAU 2",
        "Publicação do Registro": "23/01/2017",
        "Vencimento do Registro": "23/01/2027",
        "Situação do Produto": "INATIVO"
    },
    {
        "Nome do Produto": "SKINCEUTICALS AOX+ EYE GEL",
        "Processo": "25351.494991/2011-96",
        "Nome da Empresa - CNPJ": "PROCOSA PRODUTOS DE BELEZA LTDA - 33.306.929/0001-00",
        "Número do Registro": "200703735",
        "Situação": "ATIVO",
        "Vencimento": "23/01/2027",
        "link": "https://consultas.anvisa.gov.br/#/cosmeticos/registrados/25351494991201196/?dataInicial=2027-01-23&dataFinal=2027-01-23",
        "Nome da Empresa": "PROCOSA PRODUTOS DE BELEZA LTDA",
        "Número do CNPJ da Empresa": "33.306.929/0001-00",
        "Categoria": "GEL PARA ÁREA DOS OLHOS EXCETO OS DE MAQUIAGEM E/OU AÇÃO HIDRATANTE E/OU DEMAQUILANTE",
        "Publicação do Registro": "23/01/2012",
        "Vencimento do Registro": "23/01/2027",
        "Situação do Produto": "ATIVO"
    },
    {
        "Nome do Produto": "TALCO INFANTIL AGA BABY",
        "Processo": "25351.326305/2016-81",
        "Nome da Empresa - CNPJ": "HIDRANCE COSMÉTICOS LTDA - 03.992.704/0001-86",
        "Número do Registro": "243980082",
        "Situação": "INATIVO",
        "Vencimento": "23/01/2027",
        "link": "https://consultas.anvisa.gov.br/#/cosmeticos/registrados/25351326305201681/?dataInicial=2027-01-23&dataFinal=2027-01-23",
        "Nome da Empresa": "HIDRANCE COSMÉTICOS LTDA",
        "Número do CNPJ da Empresa": "03.992.704/0001-86",
        "Categoria": "TALCO INFANTIL",
        "Publicação do Registro": "23/01/2017",
        "Vencimento do Registro": "23/01/2027",
        "Situação do Produto": "INATIVO"
    },
    {
        "Nome do Produto": "TOALHAS UMEDECIDAS SENSITIVE PANVEL BABY CLUBE",
        "Processo": "25351.372314/2016-25",
        "Nome da Empresa - CNPJ": "LENÇOBRÁS INDÚSTRIA E COMÉRCIO DE LENÇOS UMEDECIDOS LTDA - 05.756.446/0001-64",
        "Número do Registro": "237550058",
        "Situação": "ATIVO",
        "Vencimento": "23/01/2027",
        "link": "https://consultas.anvisa.gov.br/#/cosmeticos/registrados/25351372314201625/?dataInicial=2027-01-23&dataFinal=2027-01-23",
        "Nome da Empresa": "LENÇOBRÁS INDÚSTRIA E COMÉRCIO DE LENÇOS UMEDECIDOS LTDA",
        "Número do CNPJ da Empresa": "05.756.446/0001-64",
        "Categoria": "PRODUTO DE LIMPEZA/HIGIENIZAÇÃO INFANTIL - GRAU 2",
        "Publicação do Registro": "23/01/2017",
        "Vencimento do Registro": "23/01/2027",
        "Situação do Produto": "ATIVO"
    },
    {
        "Nome do Produto": "TOALHAS UMEDECIDAS SMILINGUIDO BABY",
        "Processo": "25351.316439/2016-03",
        "Nome da Empresa - CNPJ": "POWER SAVE INDUSTRIA E COMERCIO DE PRODUTOS PARA HIGIENE PESSOAL E TEXTIL LTDA - EPP - 68.146.992/0001-01",
        "Número do Registro": "268250007",
        "Situação": "INATIVO",
        "Vencimento": "23/01/2027",
        "link": "https://consultas.anvisa.gov.br/#/cosmeticos/registrados/25351316439201603/?dataInicial=2027-01-23&dataFinal=2027-01-23",
        "Nome da Empresa": "POWER SAVE INDUSTRIA E COMERCIO DE PRODUTOS PARA HIGIENE PESSOAL E TEXTIL LTDA - EPP",
        "Número do CNPJ da Empresa": "68.146.992/0001-01",
        "Categoria": "LENÇOS UMEDECIDOS PARA HIGIENE INFANTIL - GRAU 2",
        "Publicação do Registro": "23/01/2017",
        "Vencimento do Registro": "23/01/2027",
        "Situação do Produto": "INATIVO"
    },
    {
        "Nome do Produto": "TOALHINHAS UMEDECIDAS SININHO",
        "Processo": "25351.320837/2016-34",
        "Nome da Empresa - CNPJ": "EUROFRAL INDÚSTRIA DE PRODUTOS HIGIÊNICOS E TERMOPLÁSTICOS LTDA - 07.125.645/0001-08",
        "Número do Registro": "246680014",
        "Situação": "INATIVO",
        "Vencimento": "23/01/2027",
        "link": "https://consultas.anvisa.gov.br/#/cosmeticos/registrados/25351320837201634/?dataInicial=2027-01-23&dataFinal=2027-01-23",
        "Nome da Empresa": "EUROFRAL INDÚSTRIA DE PRODUTOS HIGIÊNICOS E TERMOPLÁSTICOS LTDA",
        "Número do CNPJ da Empresa": "07.125.645/0001-08",
        "Categoria": "LENÇOS UMEDECIDOS PARA HIGIENE INFANTIL - GRAU 2",
        "Publicação do Registro": "23/01/2017",
        "Vencimento do Registro": "23/01/2027",
        "Situação do Produto": "INATIVO"
    },
    {
        "Nome do Produto": "TOALINHAS UMEDECIDAS HIPOPÓ BABY",
        "Processo": "25351.316449/2016-09",
        "Nome da Empresa - CNPJ": "POWER SAVE INDUSTRIA E COMERCIO DE PRODUTOS PARA HIGIENE PESSOAL E TEXTIL LTDA - EPP - 68.146.992/0001-01",
        "Número do Registro": "268250008",
        "Situação": "INATIVO",
        "Vencimento": "23/01/2027",
        "link": "https://consultas.anvisa.gov.br/#/cosmeticos/registrados/25351316449201609/?dataInicial=2027-01-23&dataFinal=2027-01-23",
        "Nome da Empresa": "POWER SAVE INDUSTRIA E COMERCIO DE PRODUTOS PARA HIGIENE PESSOAL E TEXTIL LTDA - EPP",
        "Número do CNPJ da Empresa": "68.146.992/0001-01",
        "Categoria": "LENÇOS UMEDECIDOS PARA HIGIENE INFANTIL - GRAU 2",
        "Publicação do Registro": "23/01/2017",
        "Vencimento do Registro": "23/01/2027",
        "Situação do Produto": "INATIVO"
    }
]